Workbook

Sheet README_DataQuality
A1: Item | B1: Value
A2: Historical period requested | B2: 2025-09-02 → 2026-09-24
A3: Period for which V15 verdicts are RECORDED in the package | B3: 2025-09-30 → 2026-09-03 (first catch 2025-10-01, last catch 2026-09-03)
A4: Number of recovered sessions (with recorded V15 verdicts) | B4: 229 sessions
A5: Sessions in requested period with raw data but NO usable V15 verdict | B5: 34 sessions (see Missing_History) — warm-up 20, zero-filled delivery 7, no recorded run 7
A6: Number of confirmed catch events (engine event grouping) | B6: 769 events
A7: Number of confirmed catch-DAYS (one row per symbol per confirmed session) | B7: 852 (697 single-day events + 61 two-day + 11 three-day streaks = 852)
A8: Number of unique confirmed symbols | B8: 192
A9: Catch-days with verified current prices | B9: 848
A10: Catch-days WITHOUT current prices | B10: 4 (symbol LTIM has no row on the latest session)
A11: Previously reported audit total | B11: 913 confirmed events / 193 unique symbols
A12: Recovered event total | B12: 852 catch-days (769 grouped events)
... A21: Safety check | B21: NO CODE CHANGED · NO V15 RULE CHANGED · NO DATA MODIFIED · NO REPLAY PERFORMED · NO NEW REPOSITORY CREATED · NO PUSH/COMMIT/PR/MERGE PERFORMED · NO FUTURE DATA USED TO DETERMINE HISTORICAL V15 CONFIRMATIONS · NO MISSING DATA TREATED AS ZERO · NO PRICES INVENTED · NO CATCH EVENTS INVENTED

Sheet T1_Catches
A1: Catch Date | B1: Symbol | C1: Company Name | D1: Catch Price | E1: V15 / Accumulation Score | F1: Delivery % | G1: Volume Ratio | H1: OBV | I1: OI | J1: OI Change | K1: Confirmation Gate Status | L1: Evidence / Source | M1: Scanner Evidence ID / Git Commit | N1: Event Index | O1: Streak Day | P1: Event Status
A2: 2025-10-01 | B2: APLAPOLLO | C2: APL Apollo Tubes Limited | D2: 1731.1 | E2: N/A | F2: 65.29 | G2: N/A | H2: N/A | I2: 9691150 | J2: 306950 | K2: ACCUMULATION CONFIRMED (engine verdict; per-gate values not stored) | L2: RECORDED: backtest/REAL_1YEAR_BACKTEST_RESULT.json signals[] | M2: BT:APLAPOLLO#e0d1of1 (git commit N/A) | N2: 0 | O2: 1/1 | P2: New
A3: 2025-10-01 | B3: DIVISLAB | C3: Divi's Laboratories Limited | D3: 5710 | E3: N/A | F3: 75.65 | G3: N/A | H3: N/A | I3: 2668500 | J3: 96900 | K3: ACCUMULATION CONFIRMED (engine verdict; per-gate values not stored) | L3: RECORDED: backtest/REAL_1YEAR_BACKTEST_RESULT.json signals[] | M3: BT:DIVISLAB#e0d1of2 (git commit N/A) | N3: 0 | O3: 1/2 | P3: Active
A4: 2025-10-01 | B4: FORTIS | C4: Fortis Healthcare Limited | D4: 989.65 | E4: N/A | F4: 55.55 | G4: N/A | H4: N/A | I4: 7263300 | J4: 99975 | K4: ACCUMULATION CONFIRMED (engine verdict; per-gate values not stored) | L4: RECORDED: backtest/REAL_1YEAR_BACKTEST_RESULT.json signals[] | M4: BT:FORTIS#e0d1of1 (git commit N/A) | N4: 0 | O4: 1/1 | P4: New
A5: 2025-10-01 | B5: ICICIGI | C5: ICICI Lombard General Insurance Company Limited | D5: 1903.6 | E5: N/A | F5: 70.09 | G5: N/A | H5: N/A | I5: 5046275 | J5: 77025 | K5: ACCUMULATION CONFIRMED (engine verdict; per-gate values not stored) | L5: RECORDED: backtest/REAL_1YEAR_BACKTEST_RESULT.json signals[] | M5: BT:ICICIGI#e0d1of1 (git commit N/A) | N5: 0 | O5: 1/1 | P5: New
A6: 2025-10-01 | B6: IEX | C6: Indian Energy Exchange Limited | D6: 141.18 | E6: N/A | F6: 61.21 | G6: N/A | H6: N/A | I6: 48900000 | J6: 4117500 | K6: ACCUMULATION CONFIRMED (engine verdict; per-gate values not stored) | L6: RECORDED: backtest/REAL_1YEAR_BACKTEST_RESULT.json signals[] | M6: BT:IEX#e0d1of2 (git commit N/A) | N6: 0 | O6: 1/2 | P6: Active
A7: 2025-10-01 | B7: MFSL | C7: Max Financial Services Limited | D7: 1621.9 | E7: N/A | F7: 59.75 | G7: N/A | H7: N/A | I7: 5804800 | J7: 133600 | K7: ACCUMULATION CONFIRMED (engine verdict; per-gate values not stored) | L7: RECORDED: backtest/REAL_1YEAR_BACKTEST_RESULT.json signals[] | M7: BT:MFSL#e0d1of1 (git commit N/A) | N7: 0 | O7: 1/1 | P7: New
A8: 2025-10-01 | B8: SRF | C8: SRF Limited | D8: 2907.1 | E8: N/A | F8: 51.45 | G8: N/A | H8: N/A | I8: 2878600 | J8: 75800 | K8: ACCUMULATION CONFIRMED (engine verdict; per-gate values not stored) | L8: RECORDED: backtest/REAL_1YEAR_BACKTEST_RESULT.json signals[] | M8: BT:SRF#e0d1of1 (git commit N/A) | N8: 0 | O8: 1/1 | P8: New
A9: 2025-10-01 | B9: YESBANK | C9: Yes Bank Limited | D9: 21.76 | E9: N/A | F9: 51.51 | G9: N/A | H9: N/A | I9: 804463700 | J9: 32188500 | K9: ACCUMULATION CONFIRMED (engine verdict; per-gate values not stored) | L9: RECORDED: backtest/REAL_1YEAR_BACKTEST_RESULT.json signals[] | M9: BT:YESBANK#e0d1of1 (git commit N/A) | N9: 0 | O9: 1/1 | P9: New
A10: 2025-10-03 | B10: BAJAJ-AUTO | C10: Bajaj Auto Limited | D10: 8679.5 | E10: N/A | F10: 61.94 | G10: N/A | H10: N/A | I10: 3215850 | J10: 59100 | K10: ACCUMULATION CONFIRMED (engine verdict; per-gate values not stored) | L10: RECORDED: backtest/REAL_1YEAR_BACKTEST_RESULT.json signals[] | M10: BT:BAJAJ-AUTO#e0d1of1 (git commit N/A) | N10: 0 | O10: 1/1 | P10: New
A11: 2025-10-03 | B11: DALBHARAT | C11: Dalmia Bharat Limited | D11: 2253.7 | E11: N/A | F11: 66.81 | G11: N/A | H11: N/A | I11: 2353325 | J11: 133250 | K11: ACCUMULATION CONFIRMED (engine verdict; per-gate values not stored) | L11: RECORDED: backtest/REAL_1YEAR_BACKTEST_RESULT.json signals[] | M11: BT:DALBHARAT#e0d1of1 (git commit N/A) | N11: 0 | O11: 1/1 | P11: New
A12: 2025-10-03 | B12: DELHIVERY | C12: Delhivery Limited | D12: 437.3 | E12: N/A | F12: 66.13 | G12: N/A | H12: N/A | I12: 15770000 | J12: 2116500 | K12: ACCUMULATION CONFIRMED (engine verdict; per-gate values not stored) | L12: RECORDED: backtest/REAL_1YEAR_BACKTEST_RESULT.json signals[] | M12: BT:DELHIVERY#e0d1of1 (git commit N/A) | N12: 0 | O12: 1/1 | P12: New
A13: 2025-10-03 | B13: DIVISLAB | C13: Divi's Laboratories Limited | D13: 5866 | E13: N/A | F13: 61.94 | G13: N/A | H13: N/A | I13: 2673600 | J13: 5100 | K13: ACCUMULATION CONFIRMED (engine verdict; per-gate values not stored) | L13: RECORDED: backtest/REAL_1YEAR_BACKTEST_RESULT.json signals[] | M13: BT:DIVISLAB#e0d2of2 (git commit N/A) | N13: 0 | O13: 2/2 | P13: Active
... A853: 2026-09-03 | B853: SWIGGY | C853: Swiggy Limited | D853: 269.3 | E853: N/A | F853: 62.33 | G853: N/A | H853: N/A | I853: 87054325 | J853: 10521125 | K853: ACCUMULATION CONFIRMED (engine verdict; per-gate values not stored) | L853: RECORDED: backtest/REAL_1YEAR_BACKTEST_RESULT.json signals[] | M853: BT:SWIGGY#e1d1of1 (git commit N/A) | N853: 1 | O853: 1/1 | P853: New

Sheet T2_CatchToCurrent
A1: Catch Date | B1: Symbol | C1: Catch Price | D1: Latest/Current Verified Price | E1: Current Price Date | F1: Absolute Price Change | G1: Percentage Change (%) | H1: Status | I1: Corporate-action note | J1: Event Index
A2: 2025-10-01 | B2: APLAPOLLO | C2: 1731.1 | D2: 2197 | E2: 2026-09-28 | F2: =IF(AND(ISNUMBER(C2),ISNUMBER(D2)),D2-C2,"N/A") -> 465.9 | G2: =IF(ISNUMBER(F2),F2/C2*100,"N/A") -> 26.913523 | H2: =IF(NOT(ISNUMBER(F2)),"NO CURRENT DATA",IF(F2>0,"RISEN",IF(F2<0,"FALLEN","UNCHANGED"))) -> RISEN | I2: CORPORATE ACTION STATUS UNKNOWN (no heuristic flag) | J2: 0
A3: 2025-10-01 | B3: DIVISLAB | C3: 5710 | D3: 9550 | E3: 2026-09-28 | F3: =IF(AND(ISNUMBER(C3),ISNUMBER(D3)),D3-C3,"N/A") -> 3840 | G3: =IF(ISNUMBER(F3),F3/C3*100,"N/A") -> 67.250438 | H3: =IF(NOT(ISNUMBER(F3)),"NO CURRENT DATA",IF(F3>0,"RISEN",IF(F3<0,"FALLEN","UNCHANGED"))) -> RISEN | I3: CORPORATE ACTION STATUS UNKNOWN (no heuristic flag) | J3: 0
A4: 2025-10-01 | B4: FORTIS | C4: 989.65 | D4: 830.75 | E4: 2026-09-28 | F4: =IF(AND(ISNUMBER(C4),ISNUMBER(D4)),D4-C4,"N/A") -> -158.9 | G4: =IF(ISNUMBER(F4),F4/C4*100,"N/A") -> -16.056181 | H4: =IF(NOT(ISNUMBER(F4)),"NO CURRENT DATA",IF(F4>0,"RISEN",IF(F4<0,"FALLEN","UNCHANGED"))) -> FALLEN | I4: CORPORATE ACTION STATUS UNKNOWN (no heuristic flag) | J4: 0
A5: 2025-10-01 | B5: ICICIGI | C5: 1903.6 | D5: 1540 | E5: 2026-09-28 | F5: =IF(AND(ISNUMBER(C5),ISNUMBER(D5)),D5-C5,"N/A") -> -363.6 | G5: =IF(ISNUMBER(F5),F5/C5*100,"N/A") -> -19.100651 | H5: =IF(NOT(ISNUMBER(F5)),"NO CURRENT DATA",IF(F5>0,"RISEN",IF(F5<0,"FALLEN","UNCHANGED"))) -> FALLEN | I5: CORPORATE ACTION STATUS UNKNOWN (no heuristic flag) | J5: 0
A6: 2025-10-01 | B6: IEX | C6: 141.18 | D6: 111.35 | E6: 2026-09-28 | F6: =IF(AND(ISNUMBER(C6),ISNUMBER(D6)),D6-C6,"N/A") -> -29.83 | G6: =IF(ISNUMBER(F6),F6/C6*100,"N/A") -> -21.129055 | H6: =IF(NOT(ISNUMBER(F6)),"NO CURRENT DATA",IF(F6>0,"RISEN",IF(F6<0,"FALLEN","UNCHANGED"))) -> FALLEN | I6: CORPORATE ACTION STATUS UNKNOWN (no heuristic flag) | J6: 0
A7: 2025-10-01 | B7: MFSL | C7: 1621.9 | D7: 1444 | E7: 2026-09-28 | F7: =IF(AND(ISNUMBER(C7),ISNUMBER(D7)),D7-C7,"N/A") -> -177.9 | G7: =IF(ISNUMBER(F7),F7/C7*100,"N/A") -> -10.968617 | H7: =IF(NOT(ISNUMBER(F7)),"NO CURRENT DATA",IF(F7>0,"RISEN",IF(F7<0,"FALLEN","UNCHANGED"))) -> FALLEN | I7: CORPORATE ACTION STATUS UNKNOWN (no heuristic flag) | J7: 0
A8: 2025-10-01 | B8: SRF | C8: 2907.1 | D8: 2491.5 | E8: 2026-09-28 | F8: =IF(AND(ISNUMBER(C8),ISNUMBER(D8)),D8-C8,"N/A") -> -415.6 | G8: =IF(ISNUMBER(F8),F8/C8*100,"N/A") -> -14.296034 | H8: =IF(NOT(ISNUMBER(F8)),"NO CURRENT DATA",IF(F8>0,"RISEN",IF(F8<0,"FALLEN","UNCHANGED"))) -> FALLEN | I8: CORPORATE ACTION STATUS UNKNOWN (no heuristic flag) | J8: 0
A9: 2025-10-01 | B9: YESBANK | C9: 21.76 | D9: 21.18 | E9: 2026-09-28 | F9: =IF(AND(ISNUMBER(C9),ISNUMBER(D9)),D9-C9,"N/A") -> -0.58 | G9: =IF(ISNUMBER(F9),F9/C9*100,"N/A") -> -2.6654412 | H9: =IF(NOT(ISNUMBER(F9)),"NO CURRENT DATA",IF(F9>0,"RISEN",IF(F9<0,"FALLEN","UNCHANGED"))) -> FALLEN | I9: CORPORATE ACTION STATUS UNKNOWN (no heuristic flag) | J9: 0
A10: 2025-10-03 | B10: BAJAJ-AUTO | C10: 8679.5 | D10: 11024 | E10: 2026-09-28 | F10: =IF(AND(ISNUMBER(C10),ISNUMBER(D10)),D10-C10,"N/A") -> 2344.5 | G10: =IF(ISNUMBER(F10),F10/C10*100,"N/A") -> 27.011925 | H10: =IF(NOT(ISNUMBER(F10)),"NO CURRENT DATA",IF(F10>0,"RISEN",IF(F10<0,"FALLEN","UNCHANGED"))) -> RISEN | I10: CORPORATE ACTION STATUS UNKNOWN (no heuristic flag) | J10: 0
A11: 2025-10-03 | B11: DALBHARAT | C11: 2253.7 | D11: 1651.6 | E11: 2026-09-28 | F11: =IF(AND(ISNUMBER(C11),ISNUMBER(D11)),D11-C11,"N/A") -> -602.1 | G11: =IF(ISNUMBER(F11),F11/C11*100,"N/A") -> -26.716067 | H11: =IF(NOT(ISNUMBER(F11)),"NO CURRENT DATA",IF(F11>0,"RISEN",IF(F11<0,"FALLEN","UNCHANGED"))) -> FALLEN | I11: CORPORATE ACTION STATUS UNKNOWN (no heuristic flag) | J11: 0
A12: 2025-10-03 | B12: DELHIVERY | C12: 437.3 | D12: 407.5 | E12: 2026-09-28 | F12: =IF(AND(ISNUMBER(C12),ISNUMBER(D12)),D12-C12,"N/A") -> -29.8 | G12: =IF(ISNUMBER(F12),F12/C12*100,"N/A") -> -6.8145438 | H12: =IF(NOT(ISNUMBER(F12)),"NO CURRENT DATA",IF(F12>0,"RISEN",IF(F12<0,"FALLEN","UNCHANGED"))) -> FALLEN | I12: CORPORATE ACTION STATUS UNKNOWN (no heuristic flag) | J12: 0
A13: 2025-10-03 | B13: DIVISLAB | C13: 5866 | D13: 9550 | E13: 2026-09-28 | F13: =IF(AND(ISNUMBER(C13),ISNUMBER(D13)),D13-C13,"N/A") -> 3684 | G13: =IF(ISNUMBER(F13),F13/C13*100,"N/A") -> 62.802591 | H13: =IF(NOT(ISNUMBER(F13)),"NO CURRENT DATA",IF(F13>0,"RISEN",IF(F13<0,"FALLEN","UNCHANGED"))) -> RISEN | I13: CORPORATE ACTION STATUS UNKNOWN (no heuristic flag) | J13: 0
... A45: 2025-10-10 | B45: IDFCFIRSTB | C45: 74.43 | D45: 80.55 | E45: 2026-09-28 | F45: =IF(AND(ISNUMBER(C45),ISNUMBER(D45)),D45-C45,"N/A") -> 6.12 | G45: =IF(ISNUMBER(F45),F45/C45*100,"N/A") -> 8.2224909 | H45: =IF(NOT(ISNUMBER(F45)),"NO CURRENT DATA",IF(F45>0,"RISEN",IF(F45<0,"FALLEN","UNCHANGED"))) -> RISEN | I45: CORPORATE ACTION STATUS UNKNOWN (no heuristic flag) | J45: 0
A46: 2025-10-10 | B46: LTIM | C46: 5471.5 | D46: N/A | E46: N/A | F46: =IF(AND(ISNUMBER(C46),ISNUMBER(D46)),D46-C46,"N/A") -> N/A | G46: =IF(ISNUMBER(F46),F46/C46*100,"N/A") -> N/A | H46: =IF(NOT(ISNUMBER(F46)),"NO CURRENT DATA",IF(F46>0,"RISEN",IF(F46<0,"FALLEN","UNCHANGED"))) -> NO CURRENT DATA | I46: NO PRICE AT LATEST SESSION (symbol absent) — CORPORATE ACTION STATUS UNKNOWN | J46: 0
A47: 2025-10-10 | B47: TATAPOWER | C47: 390.1 | D47: 361.9 | E47: 2026-09-28 | F47: =IF(AND(ISNUMBER(C47),ISNUMBER(D47)),D47-C47,"N/A") -> -28.2 | G47: =IF(ISNUMBER(F47),F47/C47*100,"N/A") -> -7.2289157 | H47: =IF(NOT(ISNUMBER(F47)),"NO CURRENT DATA",IF(F47>0,"RISEN",IF(F47<0,"FALLEN","UNCHANGED"))) -> FALLEN | I47: CORPORATE ACTION STATUS UNKNOWN (no heuristic flag) | J47: 0
A48: 2025-10-13 | B48: DIVISLAB | C48: 6556 | D48: 9550 | E48: 2026-09-28 | F48: =IF(AND(ISNUMBER(C48),ISNUMBER(D48)),D48-C48,"N/A") -> 2994 | G48: =IF(ISNUMBER(F48),F48/C48*100,"N/A") -> 45.66809 | H48: =IF(NOT(ISNUMBER(F48)),"NO CURRENT DATA",IF(F48>0,"RISEN",IF(F48<0,"FALLEN","UNCHANGED"))) -> RISEN | I48: CORPORATE ACTION STATUS UNKNOWN (no heuristic flag) | J48: 1
A49: 2025-10-13 | B49: FEDERALBNK | C49: 213.02 | D49: 325 | E49: 2026-09-28 | F49: =IF(AND(ISNUMBER(C49),ISNUMBER(D49)),D49-C49,"N/A") -> 111.98 | G49: =IF(ISNUMBER(F49),F49/C49*100,"N/A") -> 52.567834 | H49: =IF(NOT(ISNUMBER(F49)),"NO CURRENT DATA",IF(F49>0,"RISEN",IF(F49<0,"FALLEN","UNCHANGED"))) -> RISEN | I49: CORPORATE ACTION STATUS UNKNOWN (no heuristic flag) | J49: 0
A50: 2025-10-14 | B50: BIOCON | C50: 351.85 | D50: 374.9 | E50: 2026-09-28 | F50: =IF(AND(ISNUMBER(C50),ISNUMBER(D50)),D50-C50,"N/A") -> 23.05 | G50: =IF(ISNUMBER(F50),F50/C50*100,"N/A") -> 6.5510871 | H50: =IF(NOT(ISNUMBER(F50)),"NO CURRENT DATA",IF(F50>0,"RISEN",IF(F50<0,"FALLEN","UNCHANGED"))) -> RISEN | I50: CORPORATE ACTION STATUS UNKNOWN (no heuristic flag) | J50: 0
A51: 2025-10-14 | B51: FEDERALBNK | C51: 215.44 | D51: 325 | E51: 2026-09-28 | F51: =IF(AND(ISNUMBER(C51),ISNUMBER(D51)),D51-C51,"N/A") -> 109.56 | G51: =IF(ISNUMBER(F51),F51/C51*100,"N/A") -> 50.854066 | H51: =IF(NOT(ISNUMBER(F51)),"NO CURRENT DATA",IF(F51>0,"RISEN",IF(F51<0,"FALLEN","UNCHANGED"))) -> RISEN | I51: CORPORATE ACTION STATUS UNKNOWN (no heuristic flag) | J51: 0
A52: 2025-10-14 | B52: LAURUSLABS | C52: 877.95 | D52: 2010.7 | E52: 2026-09-28 | F52: =IF(AND(ISNUMBER(C52),ISNUMBER(D52)),D52-C52,"N/A") -> 1132.75 | G52: =IF(ISNUMBER(F52),F52/C52*100,"N/A") -> 129.02215 | H52: =IF(NOT(ISNUMBER(F52)),"NO CURRENT DATA",IF(F52>0,"RISEN",IF(F52<0,"FALLEN","UNCHANGED"))) -> RISEN | I52: CORPORATE ACTION STATUS UNKNOWN (no heuristic flag) | J52: 0
A53: 2025-10-15 | B53: 360ONE | C53: 1160.4 | D53: 1045 | E53: 2026-09-28 | F53: =IF(AND(ISNUMBER(C53),ISNUMBER(D53)),D53-C53,"N/A") -> -115.4 | G53: =IF(ISNUMBER(F53),F53/C53*100,"N/A") -> -9.9448466 | H53: =IF(NOT(ISNUMBER(F53)),"NO CURRENT DATA",IF(F53>0,"RISEN",IF(F53<0,"FALLEN","UNCHANGED"))) -> FALLEN | I53: CORPORATE ACTION STATUS UNKNOWN (no heuristic flag) | J53: 0
A54: 2025-10-15 | B54: BAJAJFINSV | C54: 2084.1 | D54: 1752 | E54: 2026-09-28 | F54: =IF(AND(ISNUMBER(C54),ISNUMBER(D54)),D54-C54,"N/A") -> -332.1 | G54: =IF(ISNUMBER(F54),F54/C54*100,"N/A") -> -15.934936 | H54: =IF(NOT(ISNUMBER(F54)),"NO CURRENT DATA",IF(F54>0,"RISEN",IF(F54<0,"FALLEN","UNCHANGED"))) -> FALLEN | I54: CORPORATE ACTION STATUS UNKNOWN (no heuristic flag) | J54: 0
A55: 2025-10-15 | B55: BAJFINANCE | C55: 1059.9 | D55: 985 | E55: 2026-09-28 | F55: =IF(AND(ISNUMBER(C55),ISNUMBER(D55)),D55-C55,"N/A") -> -74.9 | G55: =IF(ISNUMBER(F55),F55/C55*100,"N/A") -> -7.0667044 | H55: =IF(NOT(ISNUMBER(F55)),"NO CURRENT DATA",IF(F55>0,"RISEN",IF(F55<0,"FALLEN","UNCHANGED"))) -> FALLEN | I55: CORPORATE ACTION STATUS UNKNOWN (no heuristic flag) | J55: 0
A56: 2025-10-15 | B56: CIPLA | C56: 1558.7 | D56: 1383.7 | E56: 2026-09-28 | F56: =IF(AND(ISNUMBER(C56),ISNUMBER(D56)),D56-C56,"N/A") -> -175 | G56: =IF(ISNUMBER(F56),F56/C56*100,"N/A") -> -11.227305 | H56: =IF(NOT(ISNUMBER(F56)),"NO CURRENT DATA",IF(F56>0,"RISEN",IF(F56<0,"FALLEN","UNCHANGED"))) -> FALLEN | I56: CORPORATE ACTION STATUS UNKNOWN (no heuristic flag) | J56: 0
A57: 2025-10-15 | B57: HINDALCO | C57: 764.25 | D57: 955.9 | E57: 2026-09-28 | F57: =IF(AND(ISNUMBER(C57),ISNUMBER(D57)),D57-C57,"N/A") -> 191.65 | G57: =IF(ISNUMBER(F57),F57/C57*100,"N/A") -> 25.076873 | H57: =IF(NOT(ISNUMBER(F57)),"NO CURRENT DATA",IF(F57>0,"RISEN",IF(F57<0,"FALLEN","UNCHANGED"))) -> RISEN | I57: CORPORATE ACTION STATUS UNKNOWN (no heuristic flag) | J57: 1
A58: 2025-10-15 | B58: HINDPETRO | C58: 448.65 | D58: 342.45 | E58: 2026-09-28 | F58: =IF(AND(ISNUMBER(C58),ISNUMBER(D58)),D58-C58,"N/A") -> -106.2 | G58: =IF(ISNUMBER(F58),F58/C58*100,"N/A") -> -23.671013 | H58: =IF(NOT(ISNUMBER(F58)),"NO CURRENT DATA",IF(F58>0,"RISEN",IF(F58<0,"FALLEN","UNCHANGED"))) -> FALLEN | I58: CORPORATE ACTION STATUS UNKNOWN (no heuristic flag) | J58: 1
... A119: 2025-11-12 | B119: ICICIPRULI | C119: 632.95 | D119: 458.7 | E119: 2026-09-28 | F119: =IF(AND(ISNUMBER(C119),ISNUMBER(D119)),D119-C119,"N/A") -> -174.25 | G119: =IF(ISNUMBER(F119),F119/C119*100,"N/A") -> -27.529821 | H119: =IF(NOT(ISNUMBER(F119)),"NO CURRENT DATA",IF(F119>0,"RISEN",IF(F119<0,"FALLEN","UNCHANGED"))) -> FALLEN | I119: CORPORATE ACTION STATUS UNKNOWN (no heuristic flag) | J119: 0
A120: 2025-11-12 | B120: LTIM | C120: 5893.5 | D120: N/A | E120: N/A | F120: =IF(AND(ISNUMBER(C120),ISNUMBER(D120)),D120-C120,"N/A") -> N/A | G120: =IF(ISNUMBER(F120),F120/C120*100,"N/A") -> N/A | H120: =IF(NOT(ISNUMBER(F120)),"NO CURRENT DATA",IF(F120>0,"RISEN",IF(F120<0,"FALLEN","UNCHANGED"))) -> NO CURRENT DATA | I120: NO PRICE AT LATEST SESSION (symbol absent) — CORPORATE ACTION STATUS UNKNOWN | J120: 1
A121: 2025-11-12 | B121: MOTHERSON | C121: 105.92 | D121: 162.37 | E121: 2026-09-28 | F121: =IF(AND(ISNUMBER(C121),ISNUMBER(D121)),D121-C121,"N/A") -> 56.45 | G121: =IF(ISNUMBER(F121),F121/C121*100,"N/A") -> 53.29494 | H121: =IF(NOT(ISNUMBER(F121)),"NO CURRENT DATA",IF(F121>0,"RISEN",IF(F121<0,"FALLEN","UNCHANGED"))) -> RISEN | I121: CORPORATE ACTION STATUS UNKNOWN (no heuristic flag) | J121: 0
A122: 2025-11-12 | B122: SRF | C122: 2941.4 | D122: 2491.5 | E122: 2026-09-28 | F122: =IF(AND(ISNUMBER(C122),ISNUMBER(D122)),D122-C122,"N/A") -> -449.9 | G122: =IF(ISNUMBER(F122),F122/C122*100,"N/A") -> -15.295438 | H122: =IF(NOT(ISNUMBER(F122)),"NO CURRENT DATA",IF(F122>0,"RISEN",IF(F122<0,"FALLEN","UNCHANGED"))) -> FALLEN | I122: CORPORATE ACTION STATUS UNKNOWN (no heuristic flag) | J122: 2
A123: 2025-11-12 | B123: SYNGENE | C123: 663.85 | D123: 376 | E123: 2026-09-28 | F123: =IF(AND(ISNUMBER(C123),ISNUMBER(D123)),D123-C123,"N/A") -> -287.85 | G123: =IF(ISNUMBER(F123),F123/C123*100,"N/A") -> -43.360699 | H123: =IF(NOT(ISNUMBER(F123)),"NO CURRENT DATA",IF(F123>0,"RISEN",IF(F123<0,"FALLEN","UNCHANGED"))) -> FALLEN | I123: CORPORATE ACTION STATUS UNKNOWN (no heuristic flag) | J123: 0
A124: 2025-11-13 | B124: GLENMARK | C124: 1880.6 | D124: 2325.7 | E124: 2026-09-28 | F124: =IF(AND(ISNUMBER(C124),ISNUMBER(D124)),D124-C124,"N/A") -> 445.1 | G124: =IF(ISNUMBER(F124),F124/C124*100,"N/A") -> 23.667978 | H124: =IF(NOT(ISNUMBER(F124)),"NO CURRENT DATA",IF(F124>0,"RISEN",IF(F124<0,"FALLEN","UNCHANGED"))) -> RISEN | I124: CORPORATE ACTION STATUS UNKNOWN (no heuristic flag) | J124: 1
A125: 2025-11-13 | B125: NMDC | C125: 77.39 | D125: 77.43 | E125: 2026-09-28 | F125: =IF(AND(ISNUMBER(C125),ISNUMBER(D125)),D125-C125,"N/A") -> 0.04 | G125: =IF(ISNUMBER(F125),F125/C125*100,"N/A") -> 0.051686264 | H125: =IF(NOT(ISNUMBER(F125)),"NO CURRENT DATA",IF(F125>0,"RISEN",IF(F125<0,"FALLEN","UNCHANGED"))) -> RISEN | I125: CORPORATE ACTION STATUS UNKNOWN (no heuristic flag) | J125: 1
A126: 2025-11-14 | B126: ASIANPAINT | C126: 2906.4 | D126: 2420 | E126: 2026-09-28 | F126: =IF(AND(ISNUMBER(C126),ISNUMBER(D126)),D126-C126,"N/A") -> -486.4 | G126: =IF(ISNUMBER(F126),F126/C126*100,"N/A") -> -16.73548 | H126: =IF(NOT(ISNUMBER(F126)),"NO CURRENT DATA",IF(F126>0,"RISEN",IF(F126<0,"FALLEN","UNCHANGED"))) -> FALLEN | I126: CORPORATE ACTION STATUS UNKNOWN (no heuristic flag) | J126: 1
A127: 2025-11-14 | B127: AUROPHARMA | C127: 1222.5 | D127: 1697.5 | E127: 2026-09-28 | F127: =IF(AND(ISNUMBER(C127),ISNUMBER(D127)),D127-C127,"N/A") -> 475 | G127: =IF(ISNUMBER(F127),F127/C127*100,"N/A") -> 38.854806 | H127: =IF(NOT(ISNUMBER(F127)),"NO CURRENT DATA",IF(F127>0,"RISEN",IF(F127<0,"FALLEN","UNCHANGED"))) -> RISEN | I127: CORPORATE ACTION STATUS UNKNOWN (no heuristic flag) | J127: 0
A128: 2025-11-14 | B128: GLENMARK | C128: 1895.6 | D128: 2325.7 | E128: 2026-09-28 | F128: =IF(AND(ISNUMBER(C128),ISNUMBER(D128)),D128-C128,"N/A") -> 430.1 | G128: =IF(ISNUMBER(F128),F128/C128*100,"N/A") -> 22.689386 | H128: =IF(NOT(ISNUMBER(F128)),"NO CURRENT DATA",IF(F128>0,"RISEN",IF(F128<0,"FALLEN","UNCHANGED"))) -> RISEN | I128: CORPORATE ACTION STATUS UNKNOWN (no heuristic flag) | J128: 1
A129: 2025-11-14 | B129: SIEMENS | C129: 3084.2 | D129: 3785.5 | E129: 2026-09-28 | F129: =IF(AND(ISNUMBER(C129),ISNUMBER(D129)),D129-C129,"N/A") -> 701.3 | G129: =IF(ISNUMBER(F129),F129/C129*100,"N/A") -> 22.738474 | H129: =IF(NOT(ISNUMBER(F129)),"NO CURRENT DATA",IF(F129>0,"RISEN",IF(F129<0,"FALLEN","UNCHANGED"))) -> RISEN | I129: CORPORATE ACTION STATUS UNKNOWN (no heuristic flag) | J129: 0
A130: 2025-11-17 | B130: POLICYBZR | C130: 1815.7 | D130: 1151.3 | E130: 2026-09-28 | F130: =IF(AND(ISNUMBER(C130),ISNUMBER(D130)),D130-C130,"N/A") -> -664.4 | G130: =IF(ISNUMBER(F130),F130/C130*100,"N/A") -> -36.591948 | H130: =IF(NOT(ISNUMBER(F130)),"NO CURRENT DATA",IF(F130>0,"RISEN",IF(F130<0,"FALLEN","UNCHANGED"))) -> FALLEN | I130: SUSPECTED discontinuity (heuristic ≥20% 1-day move): 2026-09-24 (-36.0%) — CORPORATE ACTION STATUS UNKNOWN | J130: 0
A131: 2025-11-18 | B131: CONCOR | C131: 522.6 | D131: 450 | E131: 2026-09-28 | F131: =IF(AND(ISNUMBER(C131),ISNUMBER(D131)),D131-C131,"N/A") -> -72.6 | G131: =IF(ISNUMBER(F131),F131/C131*100,"N/A") -> -13.892078 | H131: =IF(NOT(ISNUMBER(F131)),"NO CURRENT DATA",IF(F131>0,"RISEN",IF(F131<0,"FALLEN","UNCHANGED"))) -> FALLEN | I131: CORPORATE ACTION STATUS UNKNOWN (no heuristic flag) | J131: 1
A132: 2025-11-19 | B132: TECHM | C132: 1433.9 | D132: 1542.2 | E132: 2026-09-28 | F132: =IF(AND(ISNUMBER(C132),ISNUMBER(D132)),D132-C132,"N/A") -> 108.3 | G132: =IF(ISNUMBER(F132),F132/C132*100,"N/A") -> 7.552828 | H132: =IF(NOT(ISNUMBER(F132)),"NO CURRENT DATA",IF(F132>0,"RISEN",IF(F132<0,"FALLEN","UNCHANGED"))) -> RISEN | I132: CORPORATE ACTION STATUS UNKNOWN (no heuristic flag) | J132: 2
... A171: 2025-12-17 | B171: IOC | C171: 168.16 | D171: 133.32 | E171: 2026-09-28 | F171: =IF(AND(ISNUMBER(C171),ISNUMBER(D171)),D171-C171,"N/A") -> -34.84 | G171: =IF(ISNUMBER(F171),F171/C171*100,"N/A") -> -20.718363 | H171: =IF(NOT(ISNUMBER(F171)),"NO CURRENT DATA",IF(F171>0,"RISEN",IF(F171<0,"FALLEN","UNCHANGED"))) -> FALLEN | I171: CORPORATE ACTION STATUS UNKNOWN (no heuristic flag) | J171: 5
A172: 2025-12-17 | B172: LTIM | C172: 6252.5 | D172: N/A | E172: N/A | F172: =IF(AND(ISNUMBER(C172),ISNUMBER(D172)),D172-C172,"N/A") -> N/A | G172: =IF(ISNUMBER(F172),F172/C172*100,"N/A") -> N/A | H172: =IF(NOT(ISNUMBER(F172)),"NO CURRENT DATA",IF(F172>0,"RISEN",IF(F172<0,"FALLEN","UNCHANGED"))) -> NO CURRENT DATA | I172: NO PRICE AT LATEST SESSION (symbol absent) — CORPORATE ACTION STATUS UNKNOWN | J172: 2
A173: 2025-12-17 | B173: PATANJALI | C173: 543.9 | D173: 390.8 | E173: 2026-09-28 | F173: =IF(AND(ISNUMBER(C173),ISNUMBER(D173)),D173-C173,"N/A") -> -153.1 | G173: =IF(ISNUMBER(F173),F173/C173*100,"N/A") -> -28.148557 | H173: =IF(NOT(ISNUMBER(F173)),"NO CURRENT DATA",IF(F173>0,"RISEN",IF(F173<0,"FALLEN","UNCHANGED"))) -> FALLEN | I173: CORPORATE ACTION STATUS UNKNOWN (no heuristic flag) | J173: 1
A174: 2025-12-17 | B174: SHRIRAMFIN | C174: 864.2 | D174: 976.3 | E174: 2026-09-28 | F174: =IF(AND(ISNUMBER(C174),ISNUMBER(D174)),D174-C174,"N/A") -> 112.1 | G174: =IF(ISNUMBER(F174),F174/C174*100,"N/A") -> 12.971534 | H174: =IF(NOT(ISNUMBER(F174)),"NO CURRENT DATA",IF(F174>0,"RISEN",IF(F174<0,"FALLEN","UNCHANGED"))) -> RISEN | I174: CORPORATE ACTION STATUS UNKNOWN (no heuristic flag) | J174: 2
A175: 2025-12-18 | B175: ICICIPRULI | C175: 645.65 | D175: 458.7 | E175: 2026-09-28 | F175: =IF(AND(ISNUMBER(C175),ISNUMBER(D175)),D175-C175,"N/A") -> -186.95 | G175: =IF(ISNUMBER(F175),F175/C175*100,"N/A") -> -28.955316 | H175: =IF(NOT(ISNUMBER(F175)),"NO CURRENT DATA",IF(F175>0,"RISEN",IF(F175<0,"FALLEN","UNCHANGED"))) -> FALLEN | I175: CORPORATE ACTION STATUS UNKNOWN (no heuristic flag) | J175: 2
A176: 2025-12-18 | B176: LICI | C176: 847.4 | D176: 400.65 | E176: 2026-09-28 | F176: =IF(AND(ISNUMBER(C176),ISNUMBER(D176)),D176-C176,"N/A") -> -446.75 | G176: =IF(ISNUMBER(F176),F176/C176*100,"N/A") -> -52.720085 | H176: =IF(NOT(ISNUMBER(F176)),"NO CURRENT DATA",IF(F176>0,"RISEN",IF(F176<0,"FALLEN","UNCHANGED"))) -> FALLEN | I176: SUSPECTED discontinuity (heuristic ≥20% 1-day move): 2026-05-29 (-50.4%) — CORPORATE ACTION STATUS UNKNOWN | J176: 1
A177: 2025-12-19 | B177: ASIANPAINT | C177: 2799.9 | D177: 2420 | E177: 2026-09-28 | F177: =IF(AND(ISNUMBER(C177),ISNUMBER(D177)),D177-C177,"N/A") -> -379.9 | G177: =IF(ISNUMBER(F177),F177/C177*100,"N/A") -> -13.568342 | H177: =IF(NOT(ISNUMBER(F177)),"NO CURRENT DATA",IF(F177>0,"RISEN",IF(F177<0,"FALLEN","UNCHANGED"))) -> FALLEN | I177: CORPORATE ACTION STATUS UNKNOWN (no heuristic flag) | J177: 2
A178: 2025-12-19 | B178: DELHIVERY | C178: 405.95 | D178: 407.5 | E178: 2026-09-28 | F178: =IF(AND(ISNUMBER(C178),ISNUMBER(D178)),D178-C178,"N/A") -> 1.55 | G178: =IF(ISNUMBER(F178),F178/C178*100,"N/A") -> 0.38182042 | H178: =IF(NOT(ISNUMBER(F178)),"NO CURRENT DATA",IF(F178>0,"RISEN",IF(F178<0,"FALLEN","UNCHANGED"))) -> RISEN | I178: CORPORATE ACTION STATUS UNKNOWN (no heuristic flag) | J178: 2
A179: 2025-12-19 | B179: MANAPPURAM | C179: 292.65 | D179: 313 | E179: 2026-09-28 | F179: =IF(AND(ISNUMBER(C179),ISNUMBER(D179)),D179-C179,"N/A") -> 20.35 | G179: =IF(ISNUMBER(F179),F179/C179*100,"N/A") -> 6.953699 | H179: =IF(NOT(ISNUMBER(F179)),"NO CURRENT DATA",IF(F179>0,"RISEN",IF(F179<0,"FALLEN","UNCHANGED"))) -> RISEN | I179: CORPORATE ACTION STATUS UNKNOWN (no heuristic flag) | J179: 1
A180: 2025-12-19 | B180: SONACOMS | C180: 496.8 | D180: 807.9 | E180: 2026-09-28 | F180: =IF(AND(ISNUMBER(C180),ISNUMBER(D180)),D180-C180,"N/A") -> 311.1 | G180: =IF(ISNUMBER(F180),F180/C180*100,"N/A") -> 62.620773 | H180: =IF(NOT(ISNUMBER(F180)),"NO CURRENT DATA",IF(F180>0,"RISEN",IF(F180<0,"FALLEN","UNCHANGED"))) -> RISEN | I180: CORPORATE ACTION STATUS UNKNOWN (no heuristic flag) | J180: 1
A181: 2025-12-22 | B181: IRCTC | C181: 681.65 | D181: 453.5 | E181: 2026-09-28 | F181: =IF(AND(ISNUMBER(C181),ISNUMBER(D181)),D181-C181,"N/A") -> -228.15 | G181: =IF(ISNUMBER(F181),F181/C181*100,"N/A") -> -33.470256 | H181: =IF(NOT(ISNUMBER(F181)),"NO CURRENT DATA",IF(F181>0,"RISEN",IF(F181<0,"FALLEN","UNCHANGED"))) -> FALLEN | I181: CORPORATE ACTION STATUS UNKNOWN (no heuristic flag) | J181: 1
A182: 2025-12-30 | B182: MARUTI | C182: 16647 | D182: 12008 | E182: 2026-09-28 | F182: =IF(AND(ISNUMBER(C182),ISNUMBER(D182)),D182-C182,"N/A") -> -4639 | G182: =IF(ISNUMBER(F182),F182/C182*100,"N/A") -> -27.866883 | H182: =IF(NOT(ISNUMBER(F182)),"NO CURRENT DATA",IF(F182>0,"RISEN",IF(F182<0,"FALLEN","UNCHANGED"))) -> FALLEN | I182: CORPORATE ACTION STATUS UNKNOWN (no heuristic flag) | J182: 0
A183: 2025-12-31 | B183: ABCAPITAL | C183: 357.7 | D183: 382.7 | E183: 2026-09-28 | F183: =IF(AND(ISNUMBER(C183),ISNUMBER(D183)),D183-C183,"N/A") -> 25 | G183: =IF(ISNUMBER(F183),F183/C183*100,"N/A") -> 6.989097 | H183: =IF(NOT(ISNUMBER(F183)),"NO CURRENT DATA",IF(F183>0,"RISEN",IF(F183<0,"FALLEN","UNCHANGED"))) -> RISEN | I183: CORPORATE ACTION STATUS UNKNOWN (no heuristic flag) | J183: 0
A184: 2025-12-31 | B184: BAJAJHLDNG | C184: 11328 | D184: 10800 | E184: 2026-09-28 | F184: =IF(AND(ISNUMBER(C184),ISNUMBER(D184)),D184-C184,"N/A") -> -528 | G184: =IF(ISNUMBER(F184),F184/C184*100,"N/A") -> -4.6610169 | H184: =IF(NOT(ISNUMBER(F184)),"NO CURRENT DATA",IF(F184>0,"RISEN",IF(F184<0,"FALLEN","UNCHANGED"))) -> FALLEN | I184: CORPORATE ACTION STATUS UNKNOWN (no heuristic flag) | J184: 0
... A267: 2026-01-16 | B267: ICICIPRULI | C267: 678 | D267: 458.7 | E267: 2026-09-28 | F267: =IF(AND(ISNUMBER(C267),ISNUMBER(D267)),D267-C267,"N/A") -> -219.3 | G267: =IF(ISNUMBER(F267),F267/C267*100,"N/A") -> -32.345133 | H267: =IF(NOT(ISNUMBER(F267)),"NO CURRENT DATA",IF(F267>0,"RISEN",IF(F267<0,"FALLEN","UNCHANGED"))) -> FALLEN | I267: CORPORATE ACTION STATUS UNKNOWN (no heuristic flag) | J267: 4
A268: 2026-01-16 | B268: LTIM | C268: 6308 | D268: N/A | E268: N/A | F268: =IF(AND(ISNUMBER(C268),ISNUMBER(D268)),D268-C268,"N/A") -> N/A | G268: =IF(ISNUMBER(F268),F268/C268*100,"N/A") -> N/A | H268: =IF(NOT(ISNUMBER(F268)),"NO CURRENT DATA",IF(F268>0,"RISEN",IF(F268<0,"FALLEN","UNCHANGED"))) -> NO CURRENT DATA | I268: NO PRICE AT LATEST SESSION (symbol absent) — CORPORATE ACTION STATUS UNKNOWN | J268: 3
A269: 2026-01-16 | B269: SHRIRAMFIN | C269: 995.45 | D269: 976.3 | E269: 2026-09-28 | F269: =IF(AND(ISNUMBER(C269),ISNUMBER(D269)),D269-C269,"N/A") -> -19.15 | G269: =IF(ISNUMBER(F269),F269/C269*100,"N/A") -> -1.9237531 | H269: =IF(NOT(ISNUMBER(F269)),"NO CURRENT DATA",IF(F269>0,"RISEN",IF(F269<0,"FALLEN","UNCHANGED"))) -> FALLEN | I269: CORPORATE ACTION STATUS UNKNOWN (no heuristic flag) | J269: 3
A270: 2026-01-16 | B270: TECHM | C270: 1670.5 | D270: 1542.2 | E270: 2026-09-28 | F270: =IF(AND(ISNUMBER(C270),ISNUMBER(D270)),D270-C270,"N/A") -> -128.3 | G270: =IF(ISNUMBER(F270),F270/C270*100,"N/A") -> -7.6803352 | H270: =IF(NOT(ISNUMBER(F270)),"NO CURRENT DATA",IF(F270>0,"RISEN",IF(F270<0,"FALLEN","UNCHANGED"))) -> FALLEN | I270: CORPORATE ACTION STATUS UNKNOWN (no heuristic flag) | J270: 4
A271: 2026-01-16 | B271: ULTRACEMCO | C271: 12378 | D271: 11025 | E271: 2026-09-28 | F271: =IF(AND(ISNUMBER(C271),ISNUMBER(D271)),D271-C271,"N/A") -> -1353 | G271: =IF(ISNUMBER(F271),F271/C271*100,"N/A") -> -10.930683 | H271: =IF(NOT(ISNUMBER(F271)),"NO CURRENT DATA",IF(F271>0,"RISEN",IF(F271<0,"FALLEN","UNCHANGED"))) -> FALLEN | I271: CORPORATE ACTION STATUS UNKNOWN (no heuristic flag) | J271: 0
A272: 2026-01-19 | B272: TORNTPHARM | C272: 4086.6 | D272: 4869 | E272: 2026-09-28 | F272: =IF(AND(ISNUMBER(C272),ISNUMBER(D272)),D272-C272,"N/A") -> 782.4 | G272: =IF(ISNUMBER(F272),F272/C272*100,"N/A") -> 19.1455 | H272: =IF(NOT(ISNUMBER(F272)),"NO CURRENT DATA",IF(F272>0,"RISEN",IF(F272<0,"FALLEN","UNCHANGED"))) -> RISEN | I272: CORPORATE ACTION STATUS UNKNOWN (no heuristic flag) | J272: 2
A273: 2026-01-19 | B273: UNIONBANK | C273: 177.43 | D273: 171.75 | E273: 2026-09-28 | F273: =IF(AND(ISNUMBER(C273),ISNUMBER(D273)),D273-C273,"N/A") -> -5.68 | G273: =IF(ISNUMBER(F273),F273/C273*100,"N/A") -> -3.2012625 | H273: =IF(NOT(ISNUMBER(F273)),"NO CURRENT DATA",IF(F273>0,"RISEN",IF(F273<0,"FALLEN","UNCHANGED"))) -> FALLEN | I273: CORPORATE ACTION STATUS UNKNOWN (no heuristic flag) | J273: 0
A274: 2026-01-28 | B274: BHARATFORG | C274: 1459.1 | D274: 1957 | E274: 2026-09-28 | F274: =IF(AND(ISNUMBER(C274),ISNUMBER(D274)),D274-C274,"N/A") -> 497.9 | G274: =IF(ISNUMBER(F274),F274/C274*100,"N/A") -> 34.123775 | H274: =IF(NOT(ISNUMBER(F274)),"NO CURRENT DATA",IF(F274>0,"RISEN",IF(F274<0,"FALLEN","UNCHANGED"))) -> RISEN | I274: CORPORATE ACTION STATUS UNKNOWN (no heuristic flag) | J274: 0
A275: 2026-01-28 | B275: BPCL | C275: 362.35 | D275: 302.25 | E275: 2026-09-28 | F275: =IF(AND(ISNUMBER(C275),ISNUMBER(D275)),D275-C275,"N/A") -> -60.1 | G275: =IF(ISNUMBER(F275),F275/C275*100,"N/A") -> -16.586174 | H275: =IF(NOT(ISNUMBER(F275)),"NO CURRENT DATA",IF(F275>0,"RISEN",IF(F275<0,"FALLEN","UNCHANGED"))) -> FALLEN | I275: CORPORATE ACTION STATUS UNKNOWN (no heuristic flag) | J275: 1
A276: 2026-01-28 | B276: DABUR | C276: 515.75 | D276: 385.75 | E276: 2026-09-28 | F276: =IF(AND(ISNUMBER(C276),ISNUMBER(D276)),D276-C276,"N/A") -> -130 | G276: =IF(ISNUMBER(F276),F276/C276*100,"N/A") -> -25.206011 | H276: =IF(NOT(ISNUMBER(F276)),"NO CURRENT DATA",IF(F276>0,"RISEN",IF(F276<0,"FALLEN","UNCHANGED"))) -> FALLEN | I276: CORPORATE ACTION STATUS UNKNOWN (no heuristic flag) | J276: 1
A277: 2026-01-28 | B277: DELHIVERY | C277: 407.75 | D277: 407.5 | E277: 2026-09-28 | F277: =IF(AND(ISNUMBER(C277),ISNUMBER(D277)),D277-C277,"N/A") -> -0.25 | G277: =IF(ISNUMBER(F277),F277/C277*100,"N/A") -> -0.061312078 | H277: =IF(NOT(ISNUMBER(F277)),"NO CURRENT DATA",IF(F277>0,"RISEN",IF(F277<0,"FALLEN","UNCHANGED"))) -> FALLEN | I277: CORPORATE ACTION STATUS UNKNOWN (no heuristic flag) | J277: 4
A278: 2026-01-28 | B278: GMRAIRPORT | C278: 93.91 | D278: 94.75 | E278: 2026-09-28 | F278: =IF(AND(ISNUMBER(C278),ISNUMBER(D278)),D278-C278,"N/A") -> 0.84 | G278: =IF(ISNUMBER(F278),F278/C278*100,"N/A") -> 0.89447343 | H278: =IF(NOT(ISNUMBER(F278)),"NO CURRENT DATA",IF(F278>0,"RISEN",IF(F278<0,"FALLEN","UNCHANGED"))) -> RISEN | I278: CORPORATE ACTION STATUS UNKNOWN (no heuristic flag) | J278: 2
A279: 2026-01-28 | B279: HAL | C279: 4624 | D279: 4738 | E279: 2026-09-28 | F279: =IF(AND(ISNUMBER(C279),ISNUMBER(D279)),D279-C279,"N/A") -> 114 | G279: =IF(ISNUMBER(F279),F279/C279*100,"N/A") -> 2.4653979 | H279: =IF(NOT(ISNUMBER(F279)),"NO CURRENT DATA",IF(F279>0,"RISEN",IF(F279<0,"FALLEN","UNCHANGED"))) -> RISEN | I279: CORPORATE ACTION STATUS UNKNOWN (no heuristic flag) | J279: 0
A280: 2026-01-28 | B280: HDFCAMC | C280: 2477.6 | D280: 2302.3 | E280: 2026-09-28 | F280: =IF(AND(ISNUMBER(C280),ISNUMBER(D280)),D280-C280,"N/A") -> -175.3 | G280: =IF(ISNUMBER(F280),F280/C280*100,"N/A") -> -7.0753955 | H280: =IF(NOT(ISNUMBER(F280)),"NO CURRENT DATA",IF(F280>0,"RISEN",IF(F280<0,"FALLEN","UNCHANGED"))) -> FALLEN | I280: CORPORATE ACTION STATUS UNKNOWN (no heuristic flag) | J280: 2
... A853: 2026-09-03 | B853: SWIGGY | C853: 269.3 | D853: 256 | E853: 2026-09-28 | F853: =IF(AND(ISNUMBER(C853),ISNUMBER(D853)),D853-C853,"N/A") -> -13.3 | G853: =IF(ISNUMBER(F853),F853/C853*100,"N/A") -> -4.93873 | H853: =IF(NOT(ISNUMBER(F853)),"NO CURRENT DATA",IF(F853>0,"RISEN",IF(F853<0,"FALLEN","UNCHANGED"))) -> FALLEN | I853: CORPORATE ACTION STATUS UNKNOWN (no heuristic flag) | J853: 1

Sheet T3_StockFrequency
A1: Symbol | B1: Company Name | C1: First Catch Date | D1: Last Catch Date | E1: Total Confirmed Catches (catch-days) | F1: Distinct Events | G1: All Catch Dates | H1: Catch Frequency | I1: Current/Latest Price | J1: Latest Price Date | K1: Latest Return % (last catch → current) | L1: Status (last catch) | M1: Avg Return % across all catches | N1: Catches Risen | O1: Catches Fallen
A2: 360ONE | B2: 360 ONE WAM LIMITED | C2: 2025-10-15 | D2: 2026-08-05 | E2: 10 | F2: 10 | G2: 2025-10-15; 2026-04-09; 2026-04-15; 2026-04-17; 2026-05-04; 2026-05-06; 2026-06-15; 2026-06-19; 2026-07-10; 2026-08-05 | H2: 10 catch-days in 10 event(s); 4.37 per 100 evaluated sessions (229 evaluated) | I2: 1045 | J2: 2026-09-28 | K2: -12.332215 | L2: FALLEN | M2: -5.4146688 | N2: 1 | O2: 9
A3: ABB | B3: ABB India Limited | C3: 2026-02-03 | D3: 2026-04-15 | E3: 5 | F3: 3 | G3: 2026-02-03; 2026-04-08; 2026-04-09; 2026-04-10; 2026-04-15 | H3: 5 catch-days in 3 event(s); 2.18 per 100 evaluated sessions (229 evaluated) | I3: 6972.5 | J3: 2026-09-28 | K3: 1.4476939 | L3: RISEN | M3: 7.5453692 | N3: 5 | O3: 0
A4: ABCAPITAL | B4: Aditya Birla Capital Limited | C4: 2025-12-31 | D4: 2026-09-02 | E4: 3 | F4: 3 | G4: 2025-12-31; 2026-05-20; 2026-09-02 | H4: 3 catch-days in 3 event(s); 1.31 per 100 evaluated sessions (229 evaluated) | I4: 382.7 | J4: 2026-09-28 | K4: -3.6141544 | L4: FALLEN | M4: 3.919279 | N4: 2 | O4: 1
A5: ADANIENSOL | B5: Adani Energy Solutions Limited | C5: 2026-04-17 | D5: 2026-08-14 | E5: 2 | F5: 2 | G5: 2026-04-17; 2026-08-14 | H5: 2 catch-days in 2 event(s); 0.87 per 100 evaluated sessions (229 evaluated) | I5: 1287.9 | J5: 2026-09-28 | K5: -20.303218 | L5: FALLEN | M5: -9.0363525 | N5: 1 | O5: 1
A6: ADANIENT | B6: Adani Enterprises Limited | C6: 2025-12-04 | D6: 2026-07-01 | E6: 2 | F6: 2 | G6: 2025-12-04; 2026-07-01 | H6: 2 catch-days in 2 event(s); 0.87 per 100 evaluated sessions (229 evaluated) | I6: 2831.1 | J6: 2026-09-28 | K6: -9.9408322 | L6: FALLEN | M6: 8.8534714 | N6: 1 | O6: 1
A7: ADANIPORTS | B7: Adani Ports and Special Economic Zone Limited | C7: 2025-10-16 | D7: 2026-06-17 | E7: 3 | F7: 3 | G7: 2025-10-16; 2026-04-01; 2026-06-17 | H7: 3 catch-days in 3 event(s); 1.31 per 100 evaluated sessions (229 evaluated) | I7: 1743.7 | J7: 2026-09-28 | K7: -4.6428962 | L7: FALLEN | M7: 13.025685 | N7: 2 | O7: 1
A8: ADANIPOWER | B8: Adani Power Limited | C8: 2026-04-06 | D8: 2026-04-06 | E8: 1 | F8: 1 | G8: 2026-04-06 | H8: 1 catch-days in 1 event(s); 0.44 per 100 evaluated sessions (229 evaluated) | I8: 196.14 | J8: 2026-09-28 | K8: 20.139655 | L8: RISEN | M8: 20.139655 | N8: 1 | O8: 0
A9: ALKEM | B9: Alkem Laboratories Limited | C9: 2025-11-07 | D9: 2026-08-28 | E9: 12 | F9: 11 | G9: 2025-11-07; 2026-01-07; 2026-01-12; 2026-02-09; 2026-04-15; 2026-05-29; 2026-06-30; 2026-07-03; 2026-07-07; 2026-07-14; 2026-08-27; 2026-08-28 | H9: 12 catch-days in 11 event(s); 5.24 per 100 evaluated sessions (229 evaluated) | I9: 5175 | J9: 2026-09-28 | K9: -3.3613445 | L9: FALLEN | M9: -7.5742607 | N9: 0 | O9: 12
A10: AMBER | B10: Amber Enterprises India Limited | C10: 2026-08-18 | D10: 2026-08-18 | E10: 1 | F10: 1 | G10: 2026-08-18 | H10: 1 catch-days in 1 event(s); 0.44 per 100 evaluated sessions (229 evaluated) | I10: 6990 | J10: 2026-09-28 | K10: -4.8979592 | L10: FALLEN | M10: -4.8979592 | N10: 0 | O10: 1
A11: AMBUJACEM | B11: Ambuja Cements Limited | C11: 2025-12-11 | D11: 2026-08-05 | E11: 3 | F11: 3 | G11: 2025-12-11; 2026-01-29; 2026-08-05 | H11: 3 catch-days in 3 event(s); 1.31 per 100 evaluated sessions (229 evaluated) | I11: 374.35 | J11: 2026-09-28 | K11: -15.876404 | L11: FALLEN | M11: -25.40437 | N11: 0 | O11: 3
A12: APLAPOLLO | B12: APL Apollo Tubes Limited | C12: 2025-10-01 | D12: 2026-08-28 | E12: 7 | F12: 7 | G12: 2025-10-01; 2025-12-17; 2026-01-01; 2026-01-14; 2026-06-15; 2026-08-03; 2026-08-28 | H12: 7 catch-days in 7 event(s); 3.06 per 100 evaluated sessions (229 evaluated) | I12: 2197 | J12: 2026-09-28 | K12: -3.0278955 | L12: FALLEN | M12: 15.206159 | N12: 6 | O12: 1
A13: APOLLOHOSP | B13: Apollo Hospitals Enterprise Limited | C13: 2026-01-07 | D13: 2026-07-09 | E13: 4 | F13: 4 | G13: 2026-01-07; 2026-02-06; 2026-06-09; 2026-07-09 | H13: 4 catch-days in 4 event(s); 1.75 per 100 evaluated sessions (229 evaluated) | I13: 8860 | J13: 2026-09-28 | K13: 0.16392516 | L13: RISEN | M13: 11.736151 | N13: 4 | O13: 0
... A108: LTF | B108: L&T Finance Limited | C108: 2025-10-03 | D108: 2026-05-29 | E108: 2 | F108: 2 | G108: 2025-10-03; 2026-05-29 | H108: 2 catch-days in 2 event(s); 0.87 per 100 evaluated sessions (229 evaluated) | I108: 280.85 | J108: 2026-09-28 | K108: -2.0062805 | L108: FALLEN | M108: 2.5267648 | N108: 1 | O108: 1
A109: LTIM | B109: N/A | C109: 2025-10-10 | D109: 2026-01-16 | E109: 4 | F109: 4 | G109: 2025-10-10; 2025-11-12; 2025-12-17; 2026-01-16 | H109: 4 catch-days in 4 event(s); 3.92 per 100 evaluated sessions (102 evaluated) | I109: N/A | J109: N/A | K109: N/A | L109: NO CURRENT DATA | M109: N/A | N109: 0 | O109: 0
A110: LTM | B110: LTM Limited | C110: 2026-04-02 | D110: 2026-04-16 | E110: 3 | F110: 2 | G110: 2026-04-02; 2026-04-15; 2026-04-16 | H110: 3 catch-days in 2 event(s); 2.80 per 100 evaluated sessions (107 evaluated) | I110: 4091.4 | J110: 2026-09-28 | K110: -13.501057 | L110: FALLEN | M110: -10.015483 | N110: 0 | O110: 3
A111: LUPIN | B111: Lupin Limited | C111: 2025-10-31 | D111: 2026-07-29 | E111: 8 | F111: 6 | G111: 2025-10-31; 2025-11-03; 2025-11-04; 2026-01-06; 2026-02-25; 2026-03-10; 2026-05-06; 2026-07-29 | H111: 8 catch-days in 6 event(s); 3.49 per 100 evaluated sessions (229 evaluated) | I111: 2062 | J111: 2026-09-28 | K111: -15.733551 | L111: FALLEN | M111: -5.6271283 | N111: 3 | O111: 5
A112: MANAPPURAM | B112: Manappuram Finance Limited | C112: 2025-11-10 | D112: 2026-07-31 | E112: 4 | F112: 4 | G112: 2025-11-10; 2025-12-19; 2026-07-20; 2026-07-31 | H112: 4 catch-days in 4 event(s); 1.75 per 100 evaluated sessions (229 evaluated) | I112: 313 | J112: 2026-09-28 | K112: -15.826274 | L112: FALLEN | M112: -0.85290182 | N112: 2 | O112: 2
A113: MANKIND | B113: Mankind Pharma Limited | C113: 2025-10-06 | D113: 2026-05-15 | E113: 7 | F113: 7 | G113: 2025-10-06; 2025-10-17; 2025-12-12; 2026-02-03; 2026-02-25; 2026-05-11; 2026-05-15 | H113: 7 catch-days in 7 event(s); 3.06 per 100 evaluated sessions (229 evaluated) | I113: 2435.6 | J113: 2026-09-28 | K113: -2.6927687 | L113: FALLEN | M113: 4.4083431 | N113: 3 | O113: 4
A114: MARICO | B114: Marico Limited | C114: 2026-04-01 | D114: 2026-08-03 | E114: 3 | F114: 2 | G114: 2026-04-01; 2026-04-02; 2026-08-03 | H114: 3 catch-days in 2 event(s); 1.31 per 100 evaluated sessions (229 evaluated) | I114: 813.25 | J114: 2026-09-28 | K114: -7.6848856 | L114: FALLEN | M114: 2.7887795 | N114: 2 | O114: 1
A115: MARUTI | B115: Maruti Suzuki India Limited | C115: 2025-12-30 | D115: 2026-06-30 | E115: 4 | F115: 4 | G115: 2025-12-30; 2026-05-07; 2026-06-12; 2026-06-30 | H115: 4 catch-days in 4 event(s); 1.75 per 100 evaluated sessions (229 evaluated) | I115: 12008 | J115: 2026-09-28 | K115: -14.927382 | L115: FALLEN | M115: -16.437577 | N115: 0 | O115: 4
A116: MAXHEALTH | B116: Max Healthcare Institute Limited | C116: 2026-02-10 | D116: 2026-03-20 | E116: 2 | F116: 2 | G116: 2026-02-10; 2026-03-20 | H116: 2 catch-days in 2 event(s); 0.87 per 100 evaluated sessions (229 evaluated) | I116: 1000.1 | J116: 2026-09-28 | K116: 3.6587894 | L116: RISEN | M116: 0.7819155 | N116: 1 | O116: 1
A117: MFSL | B117: Max Financial Services Limited | C117: 2025-10-01 | D117: 2026-07-29 | E117: 7 | F117: 7 | G117: 2025-10-01; 2025-11-04; 2026-01-06; 2026-02-09; 2026-02-13; 2026-03-20; 2026-07-29 | H117: 7 catch-days in 7 event(s); 3.06 per 100 evaluated sessions (229 evaluated) | I117: 1444 | J117: 2026-09-28 | K117: -4.6927596 | L117: FALLEN | M117: -13.14249 | N117: 0 | O117: 7
A118: MOTHERSON | B118: Samvardhana Motherson International Limited | C118: 2025-11-12 | D118: 2026-07-31 | E118: 8 | F118: 7 | G118: 2025-11-12; 2025-12-02; 2025-12-11; 2026-04-01; 2026-05-19; 2026-05-27; 2026-05-29; 2026-07-31 | H118: 8 catch-days in 7 event(s); 3.49 per 100 evaluated sessions (229 evaluated) | I118: 162.37 | J118: 2026-09-28 | K118: 7.708126 | L118: RISEN | M118: 29.05874 | N118: 8 | O118: 0
A119: MOTILALOFS | B119: Motilal Oswal Financial Services Limited | C119: 2026-07-09 | D119: 2026-07-09 | E119: 1 | F119: 1 | G119: 2026-07-09 | H119: 1 catch-days in 1 event(s); 0.44 per 100 evaluated sessions (229 evaluated) | I119: 1011.6 | J119: 2026-09-28 | K119: 7.331565 | L119: RISEN | M119: 7.331565 | N119: 1 | O119: 0
A120: MPHASIS | B120: MphasiS Limited | C120: 2025-10-29 | D120: 2026-08-28 | E120: 4 | F120: 4 | G120: 2025-10-29; 2026-05-29; 2026-06-17; 2026-08-28 | H120: 4 catch-days in 4 event(s); 1.75 per 100 evaluated sessions (229 evaluated) | I120: 2237.5 | J120: 2026-09-28 | K120: -8.8594705 | L120: FALLEN | M120: -9.2258849 | N120: 0 | O120: 4
A121: MUTHOOTFIN | B121: Muthoot Finance Limited | C121: 2026-01-05 | D121: 2026-07-31 | E121: 7 | F121: 6 | G121: 2026-01-05; 2026-01-06; 2026-02-03; 2026-05-13; 2026-05-29; 2026-07-06; 2026-07-31 | H121: 7 catch-days in 6 event(s); 3.06 per 100 evaluated sessions (229 evaluated) | I121: 2760 | J121: 2026-09-28 | K121: -11.527119 | L121: FALLEN | M121: -20.814611 | N121: 0 | O121: 7
... A193: ZYDUSLIFE | B193: Zydus Lifesciences Limited | C193: 2026-07-03 | D193: 2026-08-27 | E193: 2 | F193: 2 | G193: 2026-07-03; 2026-08-27 | H193: 2 catch-days in 2 event(s); 0.87 per 100 evaluated sessions (229 evaluated) | I193: 1215 | J193: 2026-09-28 | K193: 2.1695257 | L193: RISEN | M193: 4.3462042 | N193: 2 | O193: 0

Sheet T8_MostCaught
A1: Rank | B1: Symbol | C1: Company | D1: Number of Catches (catch-days) | E1: Distinct Events | F1: All Catch Dates | G1: First Catch | H1: Last Catch | I1: Latest Price | J1: Latest Return % (last catch → current)
A2: 1 | B2: IOC | C2: Indian Oil Corporation Limited | D2: 18 | E2: 15 | F2: 2025-10-06; 2025-10-09; 2025-10-15; 2025-11-11; 2025-12-12; 2025-12-17; 2025-12-31; 2026-01-28; 2026-02-02; 2026-02-03; 2026-02-04; 2026-02-25; 2026-02-27; 2026-06-15; 2026-07-02; 2026-07-07; 2026-07-15; 2026-07-16 | G2: 2025-10-06 | H2: 2026-07-16 | I2: 133.32 | J2: -5.9802539
A3: 2 | B3: DELHIVERY | C3: Delhivery Limited | D3: 15 | E3: 12 | F3: 2025-10-03; 2025-11-04; 2025-12-19; 2026-01-05; 2026-01-06; 2026-01-07; 2026-01-28; 2026-01-29; 2026-02-10; 2026-03-18; 2026-03-20; 2026-04-08; 2026-05-15; 2026-07-02; 2026-07-10 | G3: 2025-10-03 | H3: 2026-07-10 | I3: 407.5 | J3: -21.6798
A4: 3 | B4: ALKEM | C4: Alkem Laboratories Limited | D4: 12 | E4: 11 | F4: 2025-11-07; 2026-01-07; 2026-01-12; 2026-02-09; 2026-04-15; 2026-05-29; 2026-06-30; 2026-07-03; 2026-07-07; 2026-07-14; 2026-08-27; 2026-08-28 | G4: 2025-11-07 | H4: 2026-08-28 | I4: 5175 | J4: -3.3613445
A5: 4 | B5: DIVISLAB | C5: Divi's Laboratories Limited | D5: 12 | E5: 9 | F5: 2025-10-01; 2025-10-03; 2025-10-10; 2025-10-13; 2025-11-06; 2026-05-13; 2026-06-09; 2026-07-15; 2026-07-30; 2026-07-31; 2026-08-26; 2026-08-28 | G5: 2025-10-01 | H5: 2026-08-28 | I5: 9550 | J5: 3.3661652
A6: 5 | B6: BIOCON | C6: Biocon Limited | D6: 11 | E6: 10 | F6: 2025-10-14; 2025-10-29; 2025-10-30; 2025-11-03; 2025-11-06; 2026-01-07; 2026-02-03; 2026-02-25; 2026-05-11; 2026-05-14; 2026-07-03 | G6: 2025-10-14 | H6: 2026-07-03 | I6: 374.9 | J6: -12.160262
A7: 6 | B7: NTPC | C7: NTPC Limited | D7: 11 | E7: 8 | F7: 2025-10-29; 2026-01-28; 2026-01-29; 2026-02-04; 2026-02-23; 2026-02-24; 2026-03-06; 2026-03-12; 2026-04-08; 2026-04-09; 2026-08-05 | G7: 2025-10-29 | H7: 2026-08-05 | I7: 321.1 | J7: -8.2309231
A8: 7 | B8: TECHM | C8: Tech Mahindra Limited | D8: 11 | E8: 10 | F8: 2025-10-06; 2025-11-10; 2025-11-11; 2025-11-19; 2026-01-07; 2026-01-16; 2026-03-20; 2026-05-19; 2026-05-29; 2026-07-30; 2026-08-28 | G8: 2025-10-06 | H8: 2026-08-28 | I8: 1542.2 | J8: -6.0149918
A9: 8 | B9: 360ONE | C9: 360 ONE WAM LIMITED | D9: 10 | E9: 10 | F9: 2025-10-15; 2026-04-09; 2026-04-15; 2026-04-17; 2026-05-04; 2026-05-06; 2026-06-15; 2026-06-19; 2026-07-10; 2026-08-05 | G9: 2025-10-15 | H9: 2026-08-05 | I9: 1045 | J9: -12.332215
A10: 9 | B10: BRITANNIA | C10: Britannia Industries Limited | D10: 10 | E10: 7 | F10: 2025-11-06; 2025-11-07; 2026-01-05; 2026-01-06; 2026-01-30; 2026-02-11; 2026-04-08; 2026-07-01; 2026-07-02; 2026-07-29 | G10: 2025-11-06 | H10: 2026-07-29 | I10: 4915 | J10: -10.919801
A11: 10 | B11: ICICIPRULI | C11: ICICI Prudential Life Insurance Company Limited | D11: 10 | E11: 10 | F11: 2025-11-12; 2025-12-10; 2025-12-18; 2025-12-31; 2026-01-16; 2026-04-01; 2026-04-17; 2026-06-22; 2026-07-10; 2026-08-31 | G11: 2025-11-12 | H11: 2026-08-31 | I11: 458.7 | J11: -11.285176
A12: 11 | B12: PHOENIXLTD | C12: The Phoenix Mills Limited | D12: 10 | E12: 9 | F12: 2025-10-16; 2025-12-15; 2026-01-05; 2026-01-06; 2026-03-18; 2026-04-10; 2026-04-21; 2026-06-10; 2026-06-15; 2026-07-03 | G12: 2025-10-16 | H12: 2026-07-03 | I12: 1952.2 | J12: -4.6591131
A13: 12 | B13: PIDILITIND | C13: Pidilite Industries Limited | D13: 10 | E13: 9 | F13: 2025-10-08; 2025-10-17; 2026-01-05; 2026-02-04; 2026-04-10; 2026-05-07; 2026-06-12; 2026-06-15; 2026-07-15; 2026-07-17 | G13: 2025-10-08 | H13: 2026-07-17 | I13: 1503 | J13: -4.0291169
... A92: 91 | B92: LICI | C92: Life Insurance Corporation Of India | D92: 4 | E92: 3 | F92: 2025-11-03; 2025-12-18; 2026-08-11; 2026-08-12 | G92: 2025-11-03 | H92: 2026-08-12 | I92: 400.65 | J92: -3.9208633
A93: 92 | B93: LTIM | C93: N/A | D93: 4 | E93: 4 | F93: 2025-10-10; 2025-11-12; 2025-12-17; 2026-01-16 | G93: 2025-10-10 | H93: 2026-01-16 | I93: N/A | J93: N/A
A94: 93 | B94: MANAPPURAM | C94: Manappuram Finance Limited | D94: 4 | E94: 4 | F94: 2025-11-10; 2025-12-19; 2026-07-20; 2026-07-31 | G94: 2025-11-10 | H94: 2026-07-31 | I94: 313 | J94: -15.826274
A95: 94 | B95: MARUTI | C95: Maruti Suzuki India Limited | D95: 4 | E95: 4 | F95: 2025-12-30; 2026-05-07; 2026-06-12; 2026-06-30 | G95: 2025-12-30 | H95: 2026-06-30 | I95: 12008 | J95: -14.927382
A96: 95 | B96: MPHASIS | C96: MphasiS Limited | D96: 4 | E96: 4 | F96: 2025-10-29; 2026-05-29; 2026-06-17; 2026-08-28 | G96: 2025-10-29 | H96: 2026-08-28 | I96: 2237.5 | J96: -8.8594705
A97: 96 | B97: NESTLEIND | C97: Nestle India Limited | D97: 4 | E97: 4 | F97: 2026-01-05; 2026-03-10; 2026-04-01; 2026-08-31 | G97: 2026-01-05 | H97: 2026-08-31 | I97: 1346 | J97: -10.056799
A98: 97 | B98: NUVAMA | C98: Nuvama Wealth Management Limited | D98: 4 | E98: 4 | F98: 2025-11-28; 2026-03-18; 2026-05-05; 2026-05-07 | G98: 2025-11-28 | H98: 2026-05-07 | I98: 1640.6 | J98: 11.264836
A99: 98 | B99: PIIND | C99: PI Industries Limited | D99: 4 | E99: 4 | F99: 2026-03-20; 2026-04-15; 2026-04-17; 2026-08-05 | G99: 2026-03-20 | H99: 2026-08-05 | I99: 2349 | J99: -16.405694
A100: 99 | B100: RECLTD | C100: REC Limited | D100: 4 | E100: 3 | F100: 2026-01-06; 2026-03-17; 2026-03-18; 2026-07-29 | G100: 2026-01-06 | H100: 2026-07-29 | I100: 303.25 | J100: -18.971276
A101: 100 | B101: SAMMAANCAP | C101: Sammaan Capital Limited | D101: 4 | E101: 3 | F101: 2025-12-31; 2026-01-05; 2026-01-28; 2026-01-29 | G101: 2025-12-31 | H101: 2026-01-29 | I101: 138.82 | J101: -5.9293894
A102: 101 | B102: SHRIRAMFIN | C102: Shriram Finance Limited | D102: 4 | E102: 4 | F102: 2025-10-31; 2025-11-07; 2025-12-17; 2026-01-16 | G102: 2025-10-31 | H102: 2026-01-16 | I102: 976.3 | J102: -1.9237531
A103: 102 | B103: SUPREMEIND | C103: Supreme Industries Limited | D103: 4 | E103: 4 | F103: 2026-02-04; 2026-02-25; 2026-03-11; 2026-04-17 | G103: 2026-02-04 | H103: 2026-04-17 | I103: 3499.8 | J103: -5.6403343
A104: 103 | B104: TATAPOWER | C104: Tata Power Company Limited | D104: 4 | E104: 3 | F104: 2025-10-09; 2025-10-10; 2025-12-12; 2026-06-15 | G104: 2025-10-09 | H104: 2026-06-15 | I104: 361.9 | J104: -10.44296
A105: 104 | B105: TATASTEEL | C105: Tata Steel Limited | D105: 4 | E105: 3 | F105: 2026-07-31; 2026-08-03; 2026-08-10; 2026-08-26 | G105: 2026-07-31 | H105: 2026-08-26 | I105: 186.3 | J105: -0.90952609
... A193: 192 | B193: TRENT | C193: Trent Limited | D193: 1 | E193: 1 | F193: 2026-06-19 | G193: 2026-06-19 | H193: 2026-06-19 | I193: 2626 | J193: -18.085969

Sheet T4_Daily
A1: Date | B1: Total Stocks Scanned (derived) | C1: STARTING | D1: CONFIRMED (catch-days) | E1: Unique Confirmed | F1: Repeat Confirmations | G1: First-time Catches | H1: Confirmation Rate = CONFIRMED / STARTING | I1: Supplementary rate (denominator stated) | J1: Evidence Status
A2: 2025-09-02 | B2: MISSING / UNVERIFIED | C2: MISSING / UNVERIFIED | D2: MISSING / UNVERIFIED | E2: MISSING / UNVERIFIED | F2: MISSING / UNVERIFIED | G2: MISSING / UNVERIFIED | H2: MISSING / UNVERIFIED | I2: MISSING / UNVERIFIED | J2: MISSING / UNVERIFIED — warm-up: engine needs 20 prior sessions, no verdict possible
A3: 2025-09-03 | B3: MISSING / UNVERIFIED | C3: MISSING / UNVERIFIED | D3: MISSING / UNVERIFIED | E3: MISSING / UNVERIFIED | F3: MISSING / UNVERIFIED | G3: MISSING / UNVERIFIED | H3: MISSING / UNVERIFIED | I3: MISSING / UNVERIFIED | J3: MISSING / UNVERIFIED — warm-up: engine needs 20 prior sessions, no verdict possible
A4: 2025-09-04 | B4: MISSING / UNVERIFIED | C4: MISSING / UNVERIFIED | D4: MISSING / UNVERIFIED | E4: MISSING / UNVERIFIED | F4: MISSING / UNVERIFIED | G4: MISSING / UNVERIFIED | H4: MISSING / UNVERIFIED | I4: MISSING / UNVERIFIED | J4: MISSING / UNVERIFIED — warm-up: engine needs 20 prior sessions, no verdict possible
A5: 2025-09-05 | B5: MISSING / UNVERIFIED | C5: MISSING / UNVERIFIED | D5: MISSING / UNVERIFIED | E5: MISSING / UNVERIFIED | F5: MISSING / UNVERIFIED | G5: MISSING / UNVERIFIED | H5: MISSING / UNVERIFIED | I5: MISSING / UNVERIFIED | J5: MISSING / UNVERIFIED — warm-up: engine needs 20 prior sessions, no verdict possible
A6: 2025-09-08 | B6: MISSING / UNVERIFIED | C6: MISSING / UNVERIFIED | D6: MISSING / UNVERIFIED | E6: MISSING / UNVERIFIED | F6: MISSING / UNVERIFIED | G6: MISSING / UNVERIFIED | H6: MISSING / UNVERIFIED | I6: MISSING / UNVERIFIED | J6: MISSING / UNVERIFIED — warm-up: engine needs 20 prior sessions, no verdict possible
A7: 2025-09-09 | B7: MISSING / UNVERIFIED | C7: MISSING / UNVERIFIED | D7: MISSING / UNVERIFIED | E7: MISSING / UNVERIFIED | F7: MISSING / UNVERIFIED | G7: MISSING / UNVERIFIED | H7: MISSING / UNVERIFIED | I7: MISSING / UNVERIFIED | J7: MISSING / UNVERIFIED — warm-up: engine needs 20 prior sessions, no verdict possible
A8: 2025-09-10 | B8: MISSING / UNVERIFIED | C8: MISSING / UNVERIFIED | D8: MISSING / UNVERIFIED | E8: MISSING / UNVERIFIED | F8: MISSING / UNVERIFIED | G8: MISSING / UNVERIFIED | H8: MISSING / UNVERIFIED | I8: MISSING / UNVERIFIED | J8: MISSING / UNVERIFIED — warm-up: engine needs 20 prior sessions, no verdict possible
A9: 2025-09-11 | B9: MISSING / UNVERIFIED | C9: MISSING / UNVERIFIED | D9: MISSING / UNVERIFIED | E9: MISSING / UNVERIFIED | F9: MISSING / UNVERIFIED | G9: MISSING / UNVERIFIED | H9: MISSING / UNVERIFIED | I9: MISSING / UNVERIFIED | J9: MISSING / UNVERIFIED — warm-up: engine needs 20 prior sessions, no verdict possible
A10: 2025-09-12 | B10: MISSING / UNVERIFIED | C10: MISSING / UNVERIFIED | D10: MISSING / UNVERIFIED | E10: MISSING / UNVERIFIED | F10: MISSING / UNVERIFIED | G10: MISSING / UNVERIFIED | H10: MISSING / UNVERIFIED | I10: MISSING / UNVERIFIED | J10: MISSING / UNVERIFIED — warm-up: engine needs 20 prior sessions, no verdict possible
A11: 2025-09-15 | B11: MISSING / UNVERIFIED | C11: MISSING / UNVERIFIED | D11: MISSING / UNVERIFIED | E11: MISSING / UNVERIFIED | F11: MISSING / UNVERIFIED | G11: MISSING / UNVERIFIED | H11: MISSING / UNVERIFIED | I11: MISSING / UNVERIFIED | J11: MISSING / UNVERIFIED — warm-up: engine needs 20 prior sessions, no verdict possible
A12: 2025-09-16 | B12: MISSING / UNVERIFIED | C12: MISSING / UNVERIFIED | D12: MISSING / UNVERIFIED | E12: MISSING / UNVERIFIED | F12: MISSING / UNVERIFIED | G12: MISSING / UNVERIFIED | H12: MISSING / UNVERIFIED | I12: MISSING / UNVERIFIED | J12: MISSING / UNVERIFIED — warm-up: engine needs 20 prior sessions, no verdict possible
... A21: 2025-09-29 | B21: MISSING / UNVERIFIED | C21: MISSING / UNVERIFIED | D21: MISSING / UNVERIFIED | E21: MISSING / UNVERIFIED | F21: MISSING / UNVERIFIED | G21: MISSING / UNVERIFIED | H21: MISSING / UNVERIFIED | I21: MISSING / UNVERIFIED | J21: MISSING / UNVERIFIED — warm-up: engine needs 20 prior sessions, no verdict possible
A22: 2025-09-30 | B22: 2085 | C22: N/A (not stored) | D22: 0 | E22: 0 | F22: 0 | G22: 0 | H22: N/A — STARTING not recorded (CONFIRMED / STARTING) | I22: 0.000% (CONFIRMED / 2085 scanned) | J22: RECORDED — recorded engine run (REAL_1YEAR_BACKTEST_RESULT.json)
A23: 2025-10-01 | B23: 2087 | C23: N/A (not stored) | D23: 8 | E23: 8 | F23: 0 | G23: 8 | H23: N/A — STARTING not recorded (CONFIRMED / STARTING) | I23: 0.383% (CONFIRMED / 2087 scanned) | J23: RECORDED — recorded engine run (REAL_1YEAR_BACKTEST_RESULT.json)
A24: 2025-10-03 | B24: 2086 | C24: N/A (not stored) | D24: 14 | E24: 14 | F24: 2 | G24: 12 | H24: N/A — STARTING not recorded (CONFIRMED / STARTING) | I24: 0.671% (CONFIRMED / 2086 scanned) | J24: RECORDED — recorded engine run (REAL_1YEAR_BACKTEST_RESULT.json)
A25: 2025-10-06 | B25: 2086 | C25: N/A (not stored) | D25: 7 | E25: 7 | F25: 0 | G25: 7 | H25: N/A — STARTING not recorded (CONFIRMED / STARTING) | I25: 0.336% (CONFIRMED / 2086 scanned) | J25: RECORDED — recorded engine run (REAL_1YEAR_BACKTEST_RESULT.json)
A26: 2025-10-07 | B26: 2102 | C26: N/A (not stored) | D26: 5 | E26: 5 | F26: 2 | G26: 3 | H26: N/A — STARTING not recorded (CONFIRMED / STARTING) | I26: 0.238% (CONFIRMED / 2102 scanned) | J26: RECORDED — recorded engine run (REAL_1YEAR_BACKTEST_RESULT.json)
A27: 2025-10-08 | B27: 2170 | C27: N/A (not stored) | D27: 1 | E27: 1 | F27: 0 | G27: 1 | H27: N/A — STARTING not recorded (CONFIRMED / STARTING) | I27: 0.046% (CONFIRMED / 2170 scanned) | J27: RECORDED — recorded engine run (REAL_1YEAR_BACKTEST_RESULT.json)
A28: 2025-10-09 | B28: 2169 | C28: N/A (not stored) | D28: 5 | E28: 5 | F28: 1 | G28: 4 | H28: N/A — STARTING not recorded (CONFIRMED / STARTING) | I28: 0.231% (CONFIRMED / 2169 scanned) | J28: RECORDED — recorded engine run (REAL_1YEAR_BACKTEST_RESULT.json)
A29: 2025-10-10 | B29: 2166 | C29: N/A (not stored) | D29: 6 | E29: 6 | F29: 3 | G29: 3 | H29: N/A — STARTING not recorded (CONFIRMED / STARTING) | I29: 0.277% (CONFIRMED / 2166 scanned) | J29: RECORDED — recorded engine run (REAL_1YEAR_BACKTEST_RESULT.json)
A30: 2025-10-13 | B30: 2166 | C30: N/A (not stored) | D30: 2 | E30: 2 | F30: 1 | G30: 1 | H30: N/A — STARTING not recorded (CONFIRMED / STARTING) | I30: 0.092% (CONFIRMED / 2166 scanned) | J30: RECORDED — recorded engine run (REAL_1YEAR_BACKTEST_RESULT.json)
A31: 2025-10-14 | B31: 2188 | C31: N/A (not stored) | D31: 3 | E31: 3 | F31: 1 | G31: 2 | H31: N/A — STARTING not recorded (CONFIRMED / STARTING) | I31: 0.137% (CONFIRMED / 2188 scanned) | J31: RECORDED — recorded engine run (REAL_1YEAR_BACKTEST_RESULT.json)
A32: 2025-10-15 | B32: 2184 | C32: N/A (not stored) | D32: 9 | E32: 9 | F32: 4 | G32: 5 | H32: N/A — STARTING not recorded (CONFIRMED / STARTING) | I32: 0.412% (CONFIRMED / 2184 scanned) | J32: RECORDED — recorded engine run (REAL_1YEAR_BACKTEST_RESULT.json)
A33: 2025-10-16 | B33: 2181 | C33: N/A (not stored) | D33: 6 | E33: 6 | F33: 2 | G33: 4 | H33: N/A — STARTING not recorded (CONFIRMED / STARTING) | I33: 0.275% (CONFIRMED / 2181 scanned) | J33: RECORDED — recorded engine run (REAL_1YEAR_BACKTEST_RESULT.json)
... A250: 2026-09-03 | B250: 2469 | C250: N/A (not stored) | D250: 5 | E250: 5 | F250: 4 | G250: 1 | H250: N/A — STARTING not recorded (CONFIRMED / STARTING) | I250: 0.203% (CONFIRMED / 2469 scanned) | J250: RECORDED — recorded engine run (REAL_1YEAR_BACKTEST_RESULT.json)
A251: 2026-09-04 | B251: MISSING / UNVERIFIED | C251: MISSING / UNVERIFIED | D251: MISSING / UNVERIFIED | E251: MISSING / UNVERIFIED | F251: MISSING / UNVERIFIED | G251: MISSING / UNVERIFIED | H251: MISSING / UNVERIFIED | I251: MISSING / UNVERIFIED | J251: MISSING / UNVERIFIED — recorded run saw zero-filled delivery data on this date; zero events there is NOT a verified zero
A252: 2026-09-07 | B252: MISSING / UNVERIFIED | C252: MISSING / UNVERIFIED | D252: MISSING / UNVERIFIED | E252: MISSING / UNVERIFIED | F252: MISSING / UNVERIFIED | G252: MISSING / UNVERIFIED | H252: MISSING / UNVERIFIED | I252: MISSING / UNVERIFIED | J252: MISSING / UNVERIFIED — recorded run saw zero-filled delivery data on this date; zero events there is NOT a verified zero
A253: 2026-09-08 | B253: MISSING / UNVERIFIED | C253: MISSING / UNVERIFIED | D253: MISSING / UNVERIFIED | E253: MISSING / UNVERIFIED | F253: MISSING / UNVERIFIED | G253: MISSING / UNVERIFIED | H253: MISSING / UNVERIFIED | I253: MISSING / UNVERIFIED | J253: MISSING / UNVERIFIED — recorded run saw zero-filled delivery data on this date; zero events there is NOT a verified zero
A254: 2026-09-09 | B254: MISSING / UNVERIFIED | C254: MISSING / UNVERIFIED | D254: MISSING / UNVERIFIED | E254: MISSING / UNVERIFIED | F254: MISSING / UNVERIFIED | G254: MISSING / UNVERIFIED | H254: MISSING / UNVERIFIED | I254: MISSING / UNVERIFIED | J254: MISSING / UNVERIFIED — recorded run saw zero-filled delivery data on this date; zero events there is NOT a verified zero
A255: 2026-09-10 | B255: MISSING / UNVERIFIED | C255: MISSING / UNVERIFIED | D255: MISSING / UNVERIFIED | E255: MISSING / UNVERIFIED | F255: MISSING / UNVERIFIED | G255: MISSING / UNVERIFIED | H255: MISSING / UNVERIFIED | I255: MISSING / UNVERIFIED | J255: MISSING / UNVERIFIED — recorded run saw zero-filled delivery data on this date; zero events there is NOT a verified zero
A256: 2026-09-11 | B256: MISSING / UNVERIFIED | C256: MISSING / UNVERIFIED | D256: MISSING / UNVERIFIED | E256: MISSING / UNVERIFIED | F256: MISSING / UNVERIFIED | G256: MISSING / UNVERIFIED | H256: MISSING / UNVERIFIED | I256: MISSING / UNVERIFIED | J256: MISSING / UNVERIFIED — recorded run saw zero-filled delivery data on this date; zero events there is NOT a verified zero
A257: 2026-09-15 | B257: MISSING / UNVERIFIED | C257: MISSING / UNVERIFIED | D257: MISSING / UNVERIFIED | E257: MISSING / UNVERIFIED | F257: MISSING / UNVERIFIED | G257: MISSING / UNVERIFIED | H257: MISSING / UNVERIFIED | I257: MISSING / UNVERIFIED | J257: MISSING / UNVERIFIED — recorded run saw zero-filled delivery data on this date; zero events there is NOT a verified zero
A258: 2026-09-16 | B258: MISSING / UNVERIFIED | C258: MISSING / UNVERIFIED | D258: MISSING / UNVERIFIED | E258: MISSING / UNVERIFIED | F258: MISSING / UNVERIFIED | G258: MISSING / UNVERIFIED | H258: MISSING / UNVERIFIED | I258: MISSING / UNVERIFIED | J258: MISSING / UNVERIFIED — no recorded V15 run covers this date (raw files exist, no verdicts stored)
A259: 2026-09-17 | B259: MISSING / UNVERIFIED | C259: MISSING / UNVERIFIED | D259: MISSING / UNVERIFIED | E259: MISSING / UNVERIFIED | F259: MISSING / UNVERIFIED | G259: MISSING / UNVERIFIED | H259: MISSING / UNVERIFIED | I259: MISSING / UNVERIFIED | J259: MISSING / UNVERIFIED — no recorded V15 run covers this date (raw files exist, no verdicts stored)
A260: 2026-09-18 | B260: MISSING / UNVERIFIED | C260: MISSING / UNVERIFIED | D260: MISSING / UNVERIFIED | E260: MISSING / UNVERIFIED | F260: MISSING / UNVERIFIED | G260: MISSING / UNVERIFIED | H260: MISSING / UNVERIFIED | I260: MISSING / UNVERIFIED | J260: MISSING / UNVERIFIED — no recorded V15 run covers this date (raw files exist, no verdicts stored)
A261: 2026-09-21 | B261: MISSING / UNVERIFIED | C261: MISSING / UNVERIFIED | D261: MISSING / UNVERIFIED | E261: MISSING / UNVERIFIED | F261: MISSING / UNVERIFIED | G261: MISSING / UNVERIFIED | H261: MISSING / UNVERIFIED | I261: MISSING / UNVERIFIED | J261: MISSING / UNVERIFIED — no recorded V15 run covers this date (raw files exist, no verdicts stored)
A262: 2026-09-22 | B262: MISSING / UNVERIFIED | C262: MISSING / UNVERIFIED | D262: MISSING / UNVERIFIED | E262: MISSING / UNVERIFIED | F262: MISSING / UNVERIFIED | G262: MISSING / UNVERIFIED | H262: MISSING / UNVERIFIED | I262: MISSING / UNVERIFIED | J262: MISSING / UNVERIFIED — no recorded V15 run covers this date (raw files exist, no verdicts stored)
... A264: 2026-09-24 | B264: MISSING / UNVERIFIED | C264: MISSING / UNVERIFIED | D264: MISSING / UNVERIFIED | E264: MISSING / UNVERIFIED | F264: MISSING / UNVERIFIED | G264: MISSING / UNVERIFIED | H264: MISSING / UNVERIFIED | I264: MISSING / UNVERIFIED | J264: MISSING / UNVERIFIED — no recorded V15 run covers this date (raw files exist, no verdicts stored)

Sheet T5_Weekly
A1: Week (ISO) | B1: Session range | C1: Trading Sessions | D1: Verified Sessions | E1: Missing Sessions | F1: Total STARTING | G1: Total CONFIRMED (verified sessions only) | H1: Unique Confirmed Stocks | I1: Repeat Confirmations | J1: Average Confirmed per Verified Session | K1: Confirmation Rate (CONFIRMED / STARTING) | L1: Supplementary rate | M1: Risen (current) | N1: Fallen (current) | O1: Unchanged | P1: No Current Data | Q1: Up vs Down outcome
A2: 2025-W36 | B2: 2025-09-02 → 2025-09-05 | C2: 4 | D2: 0 | E2: 4 | F2: N/A (not stored) | G2: MISSING / UNVERIFIED | H2: MISSING / UNVERIFIED | I2: MISSING / UNVERIFIED | J2: MISSING / UNVERIFIED | K2: N/A — STARTING not recorded | L2: MISSING / UNVERIFIED | M2: 0 | N2: 0 | O2: 0 | P2: 0 | Q2: MISSING / UNVERIFIED
A3: 2025-W37 | B3: 2025-09-08 → 2025-09-12 | C3: 5 | D3: 0 | E3: 5 | F3: N/A (not stored) | G3: MISSING / UNVERIFIED | H3: MISSING / UNVERIFIED | I3: MISSING / UNVERIFIED | J3: MISSING / UNVERIFIED | K3: N/A — STARTING not recorded | L3: MISSING / UNVERIFIED | M3: 0 | N3: 0 | O3: 0 | P3: 0 | Q3: MISSING / UNVERIFIED
A4: 2025-W38 | B4: 2025-09-15 → 2025-09-19 | C4: 5 | D4: 0 | E4: 5 | F4: N/A (not stored) | G4: MISSING / UNVERIFIED | H4: MISSING / UNVERIFIED | I4: MISSING / UNVERIFIED | J4: MISSING / UNVERIFIED | K4: N/A — STARTING not recorded | L4: MISSING / UNVERIFIED | M4: 0 | N4: 0 | O4: 0 | P4: 0 | Q4: MISSING / UNVERIFIED
A5: 2025-W39 | B5: 2025-09-22 → 2025-09-26 | C5: 5 | D5: 0 | E5: 5 | F5: N/A (not stored) | G5: MISSING / UNVERIFIED | H5: MISSING / UNVERIFIED | I5: MISSING / UNVERIFIED | J5: MISSING / UNVERIFIED | K5: N/A — STARTING not recorded | L5: MISSING / UNVERIFIED | M5: 0 | N5: 0 | O5: 0 | P5: 0 | Q5: MISSING / UNVERIFIED
A6: 2025-W40 | B6: 2025-09-29 → 2025-10-03 | C6: 4 | D6: 3 | E6: 1 | F6: N/A (not stored) | G6: 22 | H6: 20 | I6: 2 | J6: 7.33 (÷ 3 verified sessions) | K6: N/A — STARTING not recorded | L6: 3.52 per 1,000 scanned (6,258 stock-sessions) | M6: 8 | N6: 14 | O6: 0 | P6: 0 | Q6: 8 up / 14 down
A7: 2025-W41 | B7: 2025-10-06 → 2025-10-10 | C7: 5 | D7: 5 | E7: 0 | F7: N/A (not stored) | G7: 24 | H7: 21 | I7: 6 | J7: 4.80 (÷ 5 verified sessions) | K7: N/A — STARTING not recorded | L7: 2.24 per 1,000 scanned (10,693 stock-sessions) | M7: 8 | N7: 15 | O7: 0 | P7: 1 | Q7: 8 up / 15 down
A8: 2025-W42 | B8: 2025-10-13 → 2025-10-17 | C8: 5 | D8: 5 | E8: 0 | F8: N/A (not stored) | G8: 24 | H8: 22 | I8: 10 | J8: 4.80 (÷ 5 verified sessions) | K8: N/A — STARTING not recorded | L8: 2.20 per 1,000 scanned (10,903 stock-sessions) | M8: 8 | N8: 16 | O8: 0 | P8: 0 | Q8: 8 up / 16 down
A9: 2025-W43 | B9: 2025-10-20 → 2025-10-24 | C9: 4 | D9: 4 | E9: 0 | F9: N/A (not stored) | G9: 1 | H9: 1 | I9: 1 | J9: 0.25 (÷ 4 verified sessions) | K9: N/A — STARTING not recorded | L9: 0.11 per 1,000 scanned (8,787 stock-sessions) | M9: 0 | N9: 1 | O9: 0 | P9: 0 | Q9: 0 up / 1 down
A10: 2025-W44 | B10: 2025-10-27 → 2025-10-31 | C10: 5 | D10: 5 | E10: 0 | F10: N/A (not stored) | G10: 20 | H10: 18 | I10: 5 | J10: 4.00 (÷ 5 verified sessions) | K10: N/A — STARTING not recorded | L10: 1.82 per 1,000 scanned (10,996 stock-sessions) | M10: 9 | N10: 11 | O10: 0 | P10: 0 | Q10: 9 up / 11 down
A11: 2025-W45 | B11: 2025-11-03 → 2025-11-07 | C11: 4 | D11: 4 | E11: 0 | F11: N/A (not stored) | G11: 16 | H11: 13 | I11: 10 | J11: 4.00 (÷ 4 verified sessions) | K11: N/A — STARTING not recorded | L11: 1.81 per 1,000 scanned (8,863 stock-sessions) | M11: 6 | N11: 10 | O11: 0 | P11: 0 | Q11: 6 up / 10 down
A12: 2025-W46 | B12: 2025-11-10 → 2025-11-14 | C12: 5 | D12: 5 | E12: 0 | F12: N/A (not stored) | G12: 21 | H12: 17 | I12: 11 | J12: 4.20 (÷ 5 verified sessions) | K12: N/A — STARTING not recorded | L12: 1.88 per 1,000 scanned (11,159 stock-sessions) | M12: 12 | N12: 8 | O12: 0 | P12: 1 | Q12: 12 up / 8 down
A13: 2025-W47 | B13: 2025-11-17 → 2025-11-21 | C13: 5 | D13: 5 | E13: 0 | F13: N/A (not stored) | G13: 3 | H13: 3 | I13: 2 | J13: 0.60 (÷ 5 verified sessions) | K13: N/A — STARTING not recorded | L13: 0.27 per 1,000 scanned (11,291 stock-sessions) | M13: 1 | N13: 2 | O13: 0 | P13: 0 | Q13: 1 up / 2 down
A14: 2025-W48 | B14: 2025-11-24 → 2025-11-28 | C14: 5 | D14: 5 | E14: 0 | F14: N/A (not stored) | G14: 9 | H14: 9 | I14: 4 | J14: 1.80 (÷ 5 verified sessions) | K14: N/A — STARTING not recorded | L14: 0.79 per 1,000 scanned (11,343 stock-sessions) | M14: 6 | N14: 3 | O14: 0 | P14: 0 | Q14: 6 up / 3 down
A15: 2025-W49 | B15: 2025-12-01 → 2025-12-05 | C15: 5 | D15: 5 | E15: 0 | F15: N/A (not stored) | G15: 6 | H15: 6 | I15: 4 | J15: 1.20 (÷ 5 verified sessions) | K15: N/A — STARTING not recorded | L15: 0.53 per 1,000 scanned (11,380 stock-sessions) | M15: 4 | N15: 2 | O15: 0 | P15: 0 | Q15: 4 up / 2 down
A16: 2025-W50 | B16: 2025-12-08 → 2025-12-12 | C16: 5 | D16: 5 | E16: 0 | F16: N/A (not stored) | G16: 19 | H16: 19 | I16: 16 | J16: 3.80 (÷ 5 verified sessions) | K16: N/A — STARTING not recorded | L16: 1.66 per 1,000 scanned (11,428 stock-sessions) | M16: 9 | N16: 10 | O16: 0 | P16: 0 | Q16: 9 up / 10 down
A17: 2025-W51 | B17: 2025-12-15 → 2025-12-19 | C17: 5 | D17: 5 | E17: 0 | F17: N/A (not stored) | G17: 14 | H17: 14 | I17: 14 | J17: 2.80 (÷ 5 verified sessions) | K17: N/A — STARTING not recorded | L17: 1.22 per 1,000 scanned (11,468 stock-sessions) | M17: 7 | N17: 6 | O17: 0 | P17: 1 | Q17: 7 up / 6 down
... A54: 2026-W36 | B54: 2026-08-31 → 2026-09-04 | C54: 5 | D54: 4 | E54: 1 | F54: N/A (not stored) | G54: 21 | H54: 19 | I54: 19 | J54: 5.25 (÷ 4 verified sessions) | K54: N/A — STARTING not recorded | L54: 2.12 per 1,000 scanned (9,884 stock-sessions) | M54: 0 | N54: 21 | O54: 0 | P54: 0 | Q54: 0 up / 21 down
A55: 2026-W37 | B55: 2026-09-07 → 2026-09-11 | C55: 5 | D55: 0 | E55: 5 | F55: N/A (not stored) | G55: MISSING / UNVERIFIED | H55: MISSING / UNVERIFIED | I55: MISSING / UNVERIFIED | J55: MISSING / UNVERIFIED | K55: N/A — STARTING not recorded | L55: MISSING / UNVERIFIED | M55: 0 | N55: 0 | O55: 0 | P55: 0 | Q55: MISSING / UNVERIFIED
A56: 2026-W38 | B56: 2026-09-15 → 2026-09-18 | C56: 4 | D56: 0 | E56: 4 | F56: N/A (not stored) | G56: MISSING / UNVERIFIED | H56: MISSING / UNVERIFIED | I56: MISSING / UNVERIFIED | J56: MISSING / UNVERIFIED | K56: N/A — STARTING not recorded | L56: MISSING / UNVERIFIED | M56: 0 | N56: 0 | O56: 0 | P56: 0 | Q56: MISSING / UNVERIFIED
A57: 2026-W39 | B57: 2026-09-21 → 2026-09-24 | C57: 4 | D57: 0 | E57: 4 | F57: N/A (not stored) | G57: MISSING / UNVERIFIED | H57: MISSING / UNVERIFIED | I57: MISSING / UNVERIFIED | J57: MISSING / UNVERIFIED | K57: N/A — STARTING not recorded | L57: MISSING / UNVERIFIED | M57: 0 | N57: 0 | O57: 0 | P57: 0 | Q57: MISSING / UNVERIFIED

Sheet T6_Monthly
A1: Month | B1: Session range | C1: Trading Sessions | D1: Verified Sessions | E1: Missing Sessions | F1: Total STARTING | G1: Total CONFIRMED (verified sessions only) | H1: Unique Confirmed Stocks | I1: Repeat Confirmations | J1: Average Confirmed per Verified Session | K1: Confirmation Rate (CONFIRMED / STARTING) | L1: Supplementary rate | M1: Currently Risen | N1: Currently Fallen | O1: Currently Unchanged | P1: No Current Data
A2: 2025-09 | B2: 2025-09-02 → 2025-09-30 | C2: 21 | D2: 1 | E2: 20 | F2: N/A (not stored) | G2: 0 | H2: 0 | I2: 0 | J2: 0.00 (÷ 1 verified sessions) | K2: N/A — STARTING not recorded | L2: 0.00 per 1,000 scanned (2,085 stock-sessions) | M2: 0 | N2: 0 | O2: 0 | P2: 0
A3: 2025-10 | B3: 2025-10-01 → 2025-10-31 | C3: 21 | D3: 21 | E3: 0 | F3: N/A (not stored) | G3: 91 | H3: 67 | I3: 24 | J3: 4.33 (÷ 21 verified sessions) | K3: N/A — STARTING not recorded | L3: 2.00 per 1,000 scanned (45,552 stock-sessions) | M3: 33 | N3: 57 | O3: 0 | P3: 1
A4: 2025-11 | B4: 2025-11-03 → 2025-11-28 | C4: 19 | D4: 19 | E4: 0 | F4: N/A (not stored) | G4: 49 | H4: 39 | I4: 27 | J4: 2.58 (÷ 19 verified sessions) | K4: N/A — STARTING not recorded | L4: 1.15 per 1,000 scanned (42,656 stock-sessions) | M4: 25 | N4: 23 | O4: 0 | P4: 1
A5: 2025-12 | B5: 2025-12-01 → 2025-12-31 | C5: 22 | D5: 22 | E5: 0 | F5: N/A (not stored) | G5: 50 | H5: 41 | I5: 37 | J5: 2.27 (÷ 22 verified sessions) | K5: N/A — STARTING not recorded | L5: 0.99 per 1,000 scanned (50,380 stock-sessions) | M5: 22 | N5: 27 | O5: 0 | P5: 1
A6: 2026-01 | B6: 2026-01-01 → 2026-01-30 | C6: 20 | D6: 20 | E6: 0 | F6: N/A (not stored) | G6: 109 | H6: 75 | I6: 73 | J6: 5.45 (÷ 20 verified sessions) | K6: N/A — STARTING not recorded | L6: 2.31 per 1,000 scanned (47,117 stock-sessions) | M6: 29 | N6: 79 | O6: 0 | P6: 1
A7: 2026-02 | B7: 2026-02-02 → 2026-02-27 | C7: 20 | D7: 20 | E7: 0 | F7: N/A (not stored) | G7: 84 | H7: 61 | I7: 74 | J7: 4.20 (÷ 20 verified sessions) | K7: N/A — STARTING not recorded | L7: 1.75 per 1,000 scanned (47,878 stock-sessions) | M7: 22 | N7: 62 | O7: 0 | P7: 0
A8: 2026-03 | B8: 2026-03-02 → 2026-03-30 | C8: 19 | D8: 19 | E8: 0 | F8: N/A (not stored) | G8: 40 | H8: 32 | I8: 34 | J8: 2.11 (÷ 19 verified sessions) | K8: N/A — STARTING not recorded | L8: 0.88 per 1,000 scanned (45,700 stock-sessions) | M8: 16 | N8: 24 | O8: 0 | P8: 0
A9: 2026-04 | B9: 2026-04-01 → 2026-04-30 | C9: 20 | D9: 20 | E9: 0 | F9: N/A (not stored) | G9: 117 | H9: 78 | I9: 102 | J9: 5.85 (÷ 20 verified sessions) | K9: N/A — STARTING not recorded | L9: 2.44 per 1,000 scanned (47,901 stock-sessions) | M9: 65 | N9: 52 | O9: 0 | P9: 0
A10: 2026-05 | B10: 2026-05-04 → 2026-05-29 | C10: 19 | D10: 19 | E10: 0 | F10: N/A (not stored) | G10: 70 | H10: 53 | I10: 62 | J10: 3.68 (÷ 19 verified sessions) | K10: N/A — STARTING not recorded | L10: 1.55 per 1,000 scanned (45,268 stock-sessions) | M10: 22 | N10: 48 | O10: 0 | P10: 0
A11: 2026-06 | B11: 2026-06-01 → 2026-06-30 | C11: 21 | D11: 21 | E11: 0 | F11: N/A (not stored) | G11: 66 | H11: 51 | I11: 63 | J11: 3.14 (÷ 21 verified sessions) | K11: N/A — STARTING not recorded | L11: 1.30 per 1,000 scanned (50,838 stock-sessions) | M11: 24 | N11: 42 | O11: 0 | P11: 0
A12: 2026-07 | B12: 2026-07-01 → 2026-07-31 | C12: 23 | D12: 23 | E12: 0 | F12: N/A (not stored) | G12: 90 | H12: 68 | I12: 84 | J12: 3.91 (÷ 23 verified sessions) | K12: N/A — STARTING not recorded | L12: 1.66 per 1,000 scanned (54,304 stock-sessions) | M12: 20 | N12: 70 | O12: 0 | P12: 0
A13: 2026-08 | B13: 2026-08-03 → 2026-08-31 | C13: 21 | D13: 21 | E13: 0 | F13: N/A (not stored) | G13: 79 | H13: 59 | I13: 74 | J13: 3.76 (÷ 21 verified sessions) | K13: N/A — STARTING not recorded | L13: 1.55 per 1,000 scanned (51,031 stock-sessions) | M13: 13 | N13: 66 | O13: 0 | P13: 0
A14: 2026-09 | B14: 2026-09-01 → 2026-09-24 | C14: 17 | D14: 3 | E14: 14 | F14: N/A (not stored) | G14: 7 | H14: 7 | I14: 6 | J14: 2.33 (÷ 3 verified sessions) | K14: N/A — STARTING not recorded | L14: 0.94 per 1,000 scanned (7,414 stock-sessions) | M14: 0 | N14: 7 | O14: 0 | P14: 0

Sheet T7_UpVsDown
A1: Measure | B1: Count / % | C1: Denominator / note
A2: Total confirmed catches (catch-days) | B2: =COUNTA(T2_CatchToCurrent!$H$2:$H$853) -> 852 | C2: All catch-days; no maturity filter (youngest catch 2026-09-03 is 16 sessions before 2026-09-28)
A3: Risen catches | B3: =COUNTIF(T2_CatchToCurrent!$H$2:$H$853,"RISEN") -> 291
A4: Fallen catches | B4: =COUNTIF(T2_CatchToCurrent!$H$2:$H$853,"FALLEN") -> 557
A5: Unchanged catches | B5: =COUNTIF(T2_CatchToCurrent!$H$2:$H$853,"UNCHANGED") -> 0
A6: No current data | B6: =COUNTIF(T2_CatchToCurrent!$H$2:$H$853,"NO CURRENT DATA") -> 4
A7: Catches with a valid current price | B7: =B3+B4+B5 -> 848 | C7: Denominator for % Risen / Fallen / Unchanged
A8: % Risen | B8: =B3/B7*100 -> 34.316038 | C8: of catches with valid price (B7)
A9: % Fallen | B9: =B4/B7*100 -> 65.683962 | C9: of catches with valid price (B7)
A10: % Unchanged | B10: =B5/B7*100 -> 0 | C10: of catches with valid price (B7)
A11: % No current data | B11: =B6/B2*100 -> 0.46948357 | C11: of ALL catches (B2)
A13: Supplementary: event-level view (769 events, entry = first-detection close → 2026-09-28 close; computed in Python, static)
A14: Events RISEN | B14: 260
A15: Events FALLEN | B15: 505
A16: Events UNCHANGED | B16: 0
A17: Events NO CURRENT DATA | B17: 4
A19: Supplementary: forward returns recorded by the engine run (events; NOT current price; static)
A20: 1D: computed 769/769; CA-caveat flagged 0 | B20: win rate 49.54% ; avg return 0.07% | C20: from REAL_1YEAR_BACKTEST_RESULT.json horizonStats
A21: 5D: computed 769/769; CA-caveat flagged 0 | B21: win rate 46.68% ; avg return 0.11% | C21: from REAL_1YEAR_BACKTEST_RESULT.json horizonStats
A22: 20D: computed 728/769; CA-caveat flagged 1 | B22: win rate 48.49% ; avg return 0.59% | C22: from REAL_1YEAR_BACKTEST_RESULT.json horizonStats
A23: 60D: computed 600/769; CA-caveat flagged 4 | B23: win rate 48.17% ; avg return 0.65% | C23: from REAL_1YEAR_BACKTEST_RESULT.json horizonStats
A24: 120D: computed 360/769; CA-caveat flagged 7 | B24: win rate 41.94% ; avg return -1.8% | C24: from REAL_1YEAR_BACKTEST_RESULT.json horizonStats

Sheet T9_BestWorst
A1: # | B1: Symbol | C1: Catch Date | D1: Catch Price | E1: Current Price (2026-09-28) | F1: Return % | G1: CA heuristic flag | H1: Note
A2: TOP 20 RISING CATCHES
A3: 1 | B3: LAURUSLABS | C3: 2025-10-14 | D3: 877.95 | E3: 2010.7 | F3: 129.02215
A4: 2 | B4: LAURUSLABS | C4: 2025-11-26 | D4: 986.6 | E4: 2010.7 | F4: 103.80093
A5: 3 | B5: LAURUSLABS | C5: 2026-05-04 | D5: 1166.4 | E5: 2010.7 | F5: 72.385117
A6: 4 | B6: LAURUSLABS | C6: 2026-05-06 | D6: 1177.6 | E6: 2010.7 | F6: 70.745584
A7: 5 | B7: DIVISLAB | C7: 2025-10-01 | D7: 5710 | E7: 9550 | F7: 67.250438
A8: 6 | B8: LAURUSLABS | C8: 2026-05-07 | D8: 1206.5 | E8: 2010.7 | F8: 66.655615
A9: 7 | B9: SONACOMS | C9: 2025-12-12 | D9: 492.5 | E9: 807.9 | F9: 64.040609
A10: 8 | B10: DIVISLAB | C10: 2025-10-03 | D10: 5866 | E10: 9550 | F10: 62.802591
A11: 9 | B11: SONACOMS | C11: 2025-12-19 | D11: 496.8 | E11: 807.9 | F11: 62.620773
A12: 10 | B12: SONACOMS | C12: 2026-03-17 | D12: 502.1 | E12: 807.9 | F12: 60.904202
A13: 11 | B13: LODHA | C13: 2026-04-02 | D13: 696.05 | E13: 1117.1 | F13: 60.491344
A14: 12 | B14: LODHA | C14: 2026-04-06 | D14: 710.25 | E14: 1117.1 | F14: 57.282647
... A22: 20 | B22: DIVISLAB | C22: 2025-10-13 | D22: 6556 | E22: 9550 | F22: 45.66809
A23: BOTTOM 20 FALLING CATCHES
A24: 1 | B24: CAMS | C24: 2025-10-06 | D24: 3825.5 | E24: 691.55 | F24: -81.922624 | G24: FLAG | H24: SUSPECTED discontinuity (heuristic ≥20% 1-day move): 2025-12-05 (-80.4%) — CORPORATE ACTION STATUS UNKNOWN
A25: 2 | B25: KOTAKBANK | C25: 2025-10-16 | D25: 2205.4 | E25: 401.55 | F25: -81.792419 | G25: FLAG | H25: SUSPECTED discontinuity (heuristic ≥20% 1-day move): 2026-01-14 (-80.3%) — CORPORATE ACTION STATUS UNKNOWN
A26: 3 | B26: NUVAMA | C26: 2025-11-28 | D26: 7462.5 | E26: 1640.6 | F26: -78.01541 | G26: FLAG | H26: SUSPECTED discontinuity (heuristic ≥20% 1-day move): 2025-12-26 (-80.4%) — CORPORATE ACTION STATUS UNKNOWN
A27: 4 | B27: HDFCAMC | C27: 2025-10-03 | D27: 5591 | E27: 2302.3 | F27: -58.82132 | G27: FLAG | H27: SUSPECTED discontinuity (heuristic ≥20% 1-day move): 2025-11-26 (-49.8%) — CORPORATE ACTION STATUS UNKNOWN
A28: 5 | B28: HDFCAMC | C28: 2025-10-10 | D28: 5520 | E28: 2302.3 | F28: -58.291667 | G28: FLAG | H28: SUSPECTED discontinuity (heuristic ≥20% 1-day move): 2025-11-26 (-49.8%) — CORPORATE ACTION STATUS UNKNOWN
A29: 6 | B29: LICI | C29: 2025-11-03 | D29: 919.9 | E29: 400.65 | F29: -56.446353 | G29: FLAG | H29: SUSPECTED discontinuity (heuristic ≥20% 1-day move): 2026-05-29 (-50.4%) — CORPORATE ACTION STATUS UNKNOWN
A30: 7 | B30: LICI | C30: 2025-12-18 | D30: 847.4 | E30: 400.65 | F30: -52.720085 | G30: FLAG | H30: SUSPECTED discontinuity (heuristic ≥20% 1-day move): 2026-05-29 (-50.4%) — CORPORATE ACTION STATUS UNKNOWN
A31: 8 | B31: VEDL | C31: 2025-12-12 | D31: 543.6 | E31: 259 | F31: -52.354673 | G31: FLAG | H31: SUSPECTED discontinuity (heuristic ≥20% 1-day move): 2026-04-30 (-64.9%) — CORPORATE ACTION STATUS UNKNOWN
A32: 9 | B32: VEDL | C32: 2025-10-03 | D32: 470.95 | E32: 259 | F32: -45.004778 | G32: FLAG | H32: SUSPECTED discontinuity (heuristic ≥20% 1-day move): 2026-04-30 (-64.9%) — CORPORATE ACTION STATUS UNKNOWN
A33: 10 | B33: SYNGENE | C33: 2025-11-12 | D33: 663.85 | E33: 376 | F33: -43.360699
A34: 11 | B34: SYNGENE | C34: 2025-12-12 | D34: 647 | E34: 376 | F34: -41.885626
A35: 12 | B35: IRCTC | C35: 2025-10-29 | D35: 730.65 | E35: 453.5 | F35: -37.931978
A36: 13 | B36: POLICYBZR | C36: 2026-05-20 | D36: 1830 | E36: 1151.3 | F36: -37.087432 | G36: FLAG | H36: SUSPECTED discontinuity (heuristic ≥20% 1-day move): 2026-09-24 (-36.0%) — CORPORATE ACTION STATUS UNKNOWN
A37: 14 | B37: POLICYBZR | C37: 2025-11-17 | D37: 1815.7 | E37: 1151.3 | F37: -36.591948 | G37: FLAG | H37: SUSPECTED discontinuity (heuristic ≥20% 1-day move): 2026-09-24 (-36.0%) — CORPORATE ACTION STATUS UNKNOWN
A38: 15 | B38: POLICYBZR | C38: 2026-05-19 | D38: 1804.8 | E38: 1151.3 | F38: -36.208998 | G38: FLAG | H38: SUSPECTED discontinuity (heuristic ≥20% 1-day move): 2026-09-24 (-36.0%) — CORPORATE ACTION STATUS UNKNOWN
A39: 16 | B39: WIPRO | C39: 2025-10-15 | D39: 250.21 | E39: 161.56 | F39: -35.430239
A40: 17 | B40: PATANJALI | C40: 2025-10-29 | D40: 604.7 | E40: 390.8 | F40: -35.372912
A41: 18 | B41: ITC | C41: 2025-10-16 | D41: 405.15 | E41: 265.2 | F41: -34.542762
A42: 19 | B42: POLICYBZR | C42: 2026-05-18 | D42: 1748.3 | E42: 1151.3 | F42: -34.147458 | G42: FLAG | H42: SUSPECTED discontinuity (heuristic ≥20% 1-day move): 2026-09-24 (-36.0%) — CORPORATE ACTION STATUS UNKNOWN
A43: 20 | B43: IRCTC | C43: 2025-12-22 | D43: 681.65 | E43: 453.5 | F43: -33.470256

Sheet Events_769
A1: Symbol | B1: Company | C1: Event Index | D1: First Detection Date | E1: Entry Close | F1: Latest Detection Date | G1: Latest Detection Price | H1: Streak (sessions) | I1: Event Status | J1: 1D % | K1: 5D % | L1: 20D % | M1: 60D % | N1: 120D % | O1: Current Price 2026-09-28 | P1: Entry → Current % | Q1: Recorded CA caveat in any horizon
A2: APLAPOLLO | B2: APL Apollo Tubes Limited | C2: 0 | D2: 2025-10-01 | E2: 1731.1 | F2: 2025-10-01 | G2: 1731.1 | H2: 1 | I2: New | J2: 0.41 | K2: 0.23 | L2: 3.49 | M2: 8.79 | N2: 11.89 | O2: 2197 | P2: 26.91
A3: DIVISLAB | B3: Divi's Laboratories Limited | C3: 0 | D3: 2025-10-01 | E3: 5710 | F3: 2025-10-03 | G3: 5866 | H3: 2 | I3: Active | J3: 2.73 | K3: 7.39 | L3: 18 | M3: 11.39 | N3: 4.15 | O3: 9550 | P3: 67.25
A4: FORTIS | B4: Fortis Healthcare Limited | C4: 0 | D4: 2025-10-01 | E4: 989.65 | F4: 2025-10-01 | G4: 989.65 | H4: 1 | I4: New | J4: -0.93 | K4: 8 | L4: 3.37 | M4: -11.2 | N4: -19.67 | O4: 830.75 | P4: -16.06
A5: ICICIGI | B5: ICICI Lombard General Insurance Company Limited | C5: 0 | D5: 2025-10-01 | E5: 1903.6 | F5: 2025-10-01 | G5: 1903.6 | H5: 1 | I5: New | J5: 0.42 | K5: -1.1 | L5: 4.73 | M5: 2.7 | N5: -10.14 | O5: 1540 | P5: -19.1
A6: IEX | B6: Indian Energy Exchange Limited | C6: 0 | D6: 2025-10-01 | E6: 141.18 | F6: 2025-10-03 | G6: 143.59 | H6: 2 | I6: Active | J6: 1.71 | K6: -0.54 | L6: -1.5 | M6: -6.5 | N6: -18.72 | O6: 111.35 | P6: -21.13
A7: MFSL | B7: Max Financial Services Limited | C7: 0 | D7: 2025-10-01 | E7: 1621.9 | F7: 2025-10-01 | G7: 1621.9 | H7: 1 | I7: New | J7: -1.1 | K7: -1.58 | L7: -4.65 | M7: 0.77 | N7: -8.09 | O7: 1444 | P7: -10.97
A8: SRF | B8: SRF Limited | C8: 0 | D8: 2025-10-01 | E8: 2907.1 | F8: 2025-10-01 | G8: 2907.1 | H8: 1 | I8: New | J8: 0.42 | K8: 3.09 | L8: 0.8 | M8: 4.51 | N8: -16.14 | O8: 2491.5 | P8: -14.3
A9: YESBANK | B9: Yes Bank Limited | C9: 0 | D9: 2025-10-01 | E9: 21.76 | F9: 2025-10-01 | G9: 21.76 | H9: 1 | I9: New | J9: 0.41 | K9: 3.03 | L9: 4.5 | M9: -1.79 | N9: -20.73 | O9: 21.18 | P9: -2.67
A10: BAJAJ-AUTO | B10: Bajaj Auto Limited | C10: 0 | D10: 2025-10-03 | E10: 8679.5 | F10: 2025-10-03 | G10: 8679.5 | H10: 1 | I10: New | J10: 1.3 | K10: 3.08 | L10: 2.8 | M10: 7.64 | N10: 2.49 | O10: 11024 | P10: 27.01
A11: DALBHARAT | B11: Dalmia Bharat Limited | C11: 0 | D11: 2025-10-03 | E11: 2253.7 | F11: 2025-10-03 | G11: 2253.7 | H11: 1 | I11: New | J11: -0.11 | K11: -1.15 | L11: -7.62 | M11: -5.45 | N11: -19.87 | O11: 1651.6 | P11: -26.72
A12: DELHIVERY | B12: Delhivery Limited | C12: 0 | D12: 2025-10-03 | E12: 437.3 | F12: 2025-10-03 | G12: 437.3 | H12: 1 | I12: New | J12: 5.79 | K12: 6.3 | L12: 7.99 | M12: -7.65 | N12: -1.35 | O12: 407.5 | P12: -6.81
A13: HDFCAMC | B13: HDFC Asset Management Company Limited | C13: 0 | D13: 2025-10-03 | E13: 5591 | F13: 2025-10-03 | G13: 5591 | H13: 1 | I13: New | J13: 1.25 | K13: -1.27 | L13: -3.34 | M13: -52.21 | N13: -58.14 | O13: 2302.3 | P13: -58.82 | Q13: Y
A14: HINDPETRO | B14: Hindustan Petroleum Corporation Limited | C14: 0 | D14: 2025-10-03 | E14: 446.3 | F14: 2025-10-03 | G14: 446.3 | H14: 1 | I14: New | J14: 2.24 | K14: 1.39 | L14: 8.47 | M14: 11.82 | N14: -24.82 | O14: 342.45 | P14: -23.27
A15: JINDALSTEL | B15: JINDAL STEEL LIMITED | C15: 0 | D15: 2025-10-03 | E15: 1076.5 | F15: 2025-10-03 | G15: 1076.5 | H15: 1 | I15: New | J15: -1.91 | K15: -5.69 | L15: 0.05 | M15: -2.11 | N15: 5.66 | O15: 1139.6 | P15: 5.86
A16: LTF | B16: L&T Finance Limited | C16: 0 | D16: 2025-10-03 | E16: 262.33 | F16: 2025-10-03 | G16: 262.33 | H16: 1 | I16: New | J16: -0.94 | K16: -2.4 | L16: 6.62 | M16: 20.44 | N16: -6.74 | O16: 280.85 | P16: 7.06
A17: NMDC | B17: NMDC Limited | C17: 0 | D17: 2025-10-03 | E17: 77.1 | F17: 2025-10-03 | G17: 77.1 | H17: 1 | I17: New | J17: -1.35 | K17: 0.04 | L17: -1.53 | M17: 7.87 | N17: 1.39 | O17: 77.43 | P17: 0.43
A18: PETRONET | B18: Petronet LNG Limited | C18: 0 | D18: 2025-10-03 | E18: 278.95 | F18: 2025-10-03 | G18: 278.95 | H18: 1 | I18: New | J18: 0.48 | K18: 0.9 | L18: 2.19 | M18: 1.85 | N18: -7.55 | O18: 289.85 | P18: 3.91
A19: PFC | B19: Power Finance Corporation Limited | C19: 0 | D19: 2025-10-03 | E19: 412.2 | F19: 2025-10-03 | G19: 412.2 | H19: 1 | I19: New | J19: -1.53 | K19: -2.03 | L19: -2.13 | M19: -13.78 | N19: -3.52 | O19: 330 | P19: -19.94
A20: PNB | B20: Punjab National Bank | C20: 0 | D20: 2025-10-03 | E20: 114.37 | F20: 2025-10-03 | G20: 114.37 | H20: 1 | I20: New | J20: 0.15 | K20: 2.51 | L20: 8 | M20: 8.05 | N20: -9.07 | O20: 112.6 | P20: -1.55
A21: VEDL | B21: Vedanta Limited | C21: 0 | D21: 2025-10-03 | E21: 470.95 | F21: 2025-10-03 | G21: 470.95 | H21: 1 | I21: New | J21: -0.03 | K21: 2.39 | L21: 8.93 | M21: 28.34 | N21: 43.79 | O21: 259 | P21: -45
A22: CAMS | B22: Computer Age Management Services Limited | C22: 0 | D22: 2025-10-06 | E22: 3825.5 | F22: 2025-10-06 | G22: 3825.5 | H22: 1 | I22: New | J22: -0.65 | K22: 1.12 | L22: -0.64 | M22: -80.78 | N22: -82.72 | O22: 691.55 | P22: -81.92 | Q22: Y
A23: CYIENT | B23: Cyient Limited | C23: 0 | D23: 2025-10-06 | E23: 1180.6 | F23: 2025-10-06 | G23: 1180.6 | H23: 1 | I23: New | J23: -0.14 | K23: -1.5 | L23: -2.03 | M23: -6.06 | N23: -31.83 | O23: 1082.3 | P23: -8.33
A24: IOC | B24: Indian Oil Corporation Limited | C24: 0 | D24: 2025-10-06 | E24: 154.84 | F24: 2025-10-06 | G24: 154.84 | H24: 1 | I24: New | J24: -0.3 | K24: 0.27 | L24: 9.31 | M24: 7.13 | N24: -13.38 | O24: 133.32 | P24: -13.9
A25: MANKIND | B25: Mankind Pharma Limited | C25: 0 | D25: 2025-10-06 | E25: 2456.3 | F25: 2025-10-06 | G25: 2456.3 | H25: 1 | I25: New | J25: 0.99 | K25: -0.56 | L25: -3.53 | M25: -11.88 | N25: -18.64 | O25: 2435.6 | P25: -0.84
A26: TATACONSUM | B26: TATA CONSUMER PRODUCTS LIMITED | C26: 0 | D26: 2025-10-06 | E26: 1142.1 | F26: 2025-10-06 | G26: 1142.1 | H26: 1 | I26: New | J26: -1.94 | K26: -2.2 | L26: 3.26 | M26: 3.05 | N26: -8.76 | O26: 960 | P26: -15.94
A27: TECHM | B27: Tech Mahindra Limited | C27: 0 | D27: 2025-10-06 | E27: 1439.3 | F27: 2025-10-06 | G27: 1439.3 | H27: 1 | I27: New | J27: -0.03 | K27: 0.81 | L27: -2.09 | M27: 11.7 | N27: 0.15 | O27: 1542.2 | P27: 7.15
A28: TORNTPHARM | B28: Torrent Pharmaceuticals Limited | C28: 0 | D28: 2025-10-06 | E28: 3526 | F28: 2025-10-07 | G28: 3536.9 | H28: 2 | I28: Active | J28: 0.31 | K28: -0.22 | L28: 1.39 | M28: 9.14 | N28: 13.08 | O28: 4869 | P28: 38.09
A29: LODHA | B29: Lodha Developers Limited | C29: 0 | D29: 2025-10-07 | E29: 1145 | F29: 2025-10-07 | G29: 1145 | H29: 1 | I29: New | J29: -1.42 | K29: -0.26 | L29: 7.64 | M29: -5.18 | N29: -37.97 | O29: 1117.1 | P29: -2.44
A30: UNOMINDA | B30: UNO Minda Limited | C30: 0 | D30: 2025-10-07 | E30: 1366.3 | F30: 2025-10-07 | G30: 1366.3 | H30: 1 | I30: New | J30: -4.02 | K30: -13.24 | L30: -9.7 | M30: -3.3 | N30: -23.27 | O30: 1173 | P30: -14.15
A31: VOLTAS | B31: Voltas Limited | C31: 0 | D31: 2025-10-07 | E31: 1372.2 | F31: 2025-10-07 | G31: 1372.2 | H31: 1 | I31: New | J31: -0.36 | K31: 1.42 | L31: -5.82 | M31: 4.23 | N31: -8.76 | O31: 1135.5 | P31: -17.25
A32: YESBANK | B32: Yes Bank Limited | C32: 1 | D32: 2025-10-07 | E32: 22.22 | F32: 2025-10-07 | G32: 22.22 | H32: 1 | I32: New | J32: -0.81 | K32: 4.95 | L32: 1.85 | M32: 0.32 | N32: -18.32 | O32: 21.18 | P32: -4.68
A33: PIDILITIND | B33: Pidilite Industries Limited | C33: 0 | D33: 2025-10-08 | E33: 1493.7 | F33: 2025-10-08 | G33: 1493.7 | H33: 1 | I33: New | J33: 1.12 | K33: 0.48 | L33: -2.6 | M33: 0.76 | N33: -13.3 | O33: 1503 | P33: 0.62
A34: DRREDDY | B34: Dr. Reddy's Laboratories Limited | C34: 0 | D34: 2025-10-09 | E34: 1246.1 | F34: 2025-10-09 | G34: 1246.1 | H34: 1 | I34: New | J34: 1.47 | K34: -0.47 | L34: -3.8 | M34: 0.81 | N34: -4.39 | O34: 1221 | P34: -2.01
... A40: DIVISLAB | B40: Divi's Laboratories Limited | C40: 1 | D40: 2025-10-10 | E40: 6474.5 | F40: 2025-10-13 | G40: 6556 | H40: 2 | I40: Active | J40: 1.26 | K40: 2.27 | L40: 1 | M40: 2.59 | N40: -8.06 | O40: 9550 | P40: 47.5
A41: HDFCAMC | B41: HDFC Asset Management Company Limited | C41: 1 | D41: 2025-10-10 | E41: 5520 | F41: 2025-10-10 | G41: 5520 | H41: 1 | I41: New | J41: 2.7 | K41: 3.54 | L41: -0.72 | M41: -52.45 | N41: -54.44 | O41: 2302.3 | P41: -58.29 | Q41: Y
A42: IDFCFIRSTB | B42: IDFC First Bank Limited | C42: 0 | D42: 2025-10-10 | E42: 74.43 | F42: 2025-10-10 | G42: 74.43 | H42: 1 | I42: New | J42: -0.97 | K42: -3.43 | L42: 8.41 | M42: 13.4 | N42: -12.29 | O42: 80.55 | P42: 8.22
A43: LTIM | B43: N/A | C43: 0 | D43: 2025-10-10 | E43: 5471.5 | F43: 2025-10-10 | G43: 5471.5 | H43: 1 | I43: New | J43: 0.48 | K43: 2.44 | L43: 4.37 | M43: 11.52 | N43: INSUFFICIENT_FUTURE_DATA | O43: N/A | P43: N/A
A44: FEDERALBNK | B44: The Federal Bank Limited | C44: 0 | D44: 2025-10-13 | E44: 213.02 | F44: 2025-10-14 | G44: 215.44 | H44: 2 | I44: Active | J44: 1.14 | K44: 6.6 | L44: 12.17 | M44: 20.06 | N44: 36.94 | O44: 325 | P44: 52.57
A45: BIOCON | B45: Biocon Limited | C45: 0 | D45: 2025-10-14 | E45: 351.85 | F45: 2025-10-14 | G45: 351.85 | H45: 1 | I45: New | J45: 1.29 | K45: 4.05 | L45: 18.52 | M45: 7.89 | N45: -1.95 | O45: 374.9 | P45: 6.55
A46: LAURUSLABS | B46: Laurus Labs Limited | C46: 0 | D46: 2025-10-14 | E46: 877.95 | F46: 2025-10-14 | G46: 877.95 | H46: 1 | I46: New | J46: -0.3 | K46: 5.23 | L46: 13.57 | M46: 23.36 | N46: 23.9 | O46: 2010.7 | P46: 129.02
A47: 360ONE | B47: 360 ONE WAM LIMITED | C47: 0 | D47: 2025-10-15 | E47: 1160.4 | F47: 2025-10-15 | G47: 1160.4 | H47: 1 | I47: New | J47: 0.98 | K47: 1.59 | L47: -8.19 | M47: -2.58 | N47: -9 | O47: 1045 | P47: -9.94
A48: BAJAJFINSV | B48: Bajaj Finserv Limited | C48: 0 | D48: 2025-10-15 | E48: 2084.1 | F48: 2025-10-16 | G48: 2090.2 | H48: 2 | I48: Active | J48: 0.29 | K48: 4.44 | L48: -0.88 | M48: -4.09 | N48: -12.39 | O48: 1752 | P48: -15.93
A49: BAJFINANCE | B49: Bajaj Finance Limited | C49: 0 | D49: 2025-10-15 | E49: 1059.9 | F49: 2025-10-15 | G49: 1059.9 | H49: 1 | I49: New | J49: 0.55 | K49: 3.23 | L49: -3.91 | M49: -10.19 | N49: -13.85 | O49: 985 | P49: -7.07
A50: CIPLA | B50: Cipla Limited | C50: 0 | D50: 2025-10-15 | E50: 1558.7 | F50: 2025-10-15 | G50: 1558.7 | H50: 1 | I50: New | J50: 0.69 | K50: 5.54 | L50: -1.71 | M50: -6 | N50: -21.28 | O50: 1383.7 | P50: -11.23
A51: HINDALCO | B51: Hindalco Industries Limited | C51: 1 | D51: 2025-10-15 | E51: 764.25 | F51: 2025-10-15 | G51: 764.25 | H51: 1 | I51: New | J51: 2.07 | K51: 3.68 | L51: 5.16 | M51: 20.4 | N51: 32.35 | O51: 955.9 | P51: 25.08
A52: HINDPETRO | B52: Hindustan Petroleum Corporation Limited | C52: 1 | D52: 2025-10-15 | E52: 448.65 | F52: 2025-10-15 | G52: 448.65 | H52: 1 | I52: New | J52: 0.74 | K52: -1.77 | L52: 7.27 | M52: 0.53 | N52: -18.28 | O52: 342.45 | P52: -23.67
A53: IOC | B53: Indian Oil Corporation Limited | C53: 2 | D53: 2025-10-15 | E53: 153.69 | F53: 2025-10-15 | G53: 153.69 | H53: 1 | I53: New | J53: -0.01 | K53: -2.32 | L53: 11.43 | M53: 2.96 | N53: -5.51 | O53: 133.32 | P53: -13.25
A54: SRF | B54: SRF Limited | C54: 1 | D54: 2025-10-15 | E54: 3088.6 | F54: 2025-10-15 | G54: 3088.6 | H54: 1 | I54: New | J54: 3.28 | K54: -0.36 | L54: -8.08 | M54: -1.38 | N54: -19.04 | O54: 2491.5 | P54: -19.33
A55: WIPRO | B55: Wipro Limited | C55: 0 | D55: 2025-10-15 | E55: 250.21 | F55: 2025-10-15 | G55: 250.21 | H55: 1 | I55: New | J55: 1.44 | K55: -2.36 | L55: -2.33 | M55: 5.15 | N55: -16.17 | O55: 161.56 | P55: -35.43
... A57: ITC | B57: ITC Limited | C57: 0 | D57: 2025-10-16 | E57: 405.15 | F57: 2025-10-16 | G57: 405.15 | H57: 1 | I57: New | J57: 1.73 | K57: 2.88 | L57: 0.48 | M57: -17.39 | N57: -25.11 | O57: 265.2 | P57: -34.54
A58: KOTAKBANK | B58: Kotak Mahindra Bank Limited | C58: 0 | D58: 2025-10-16 | E58: 2205.4 | F58: 2025-10-16 | G58: 2205.4 | H58: 1 | I58: New | J58: 0.02 | K58: -0.83 | L58: -4.65 | M58: -3.3 | N58: -82.81 | O58: 401.55 | P58: -81.79 | Q58: Y
A59: PHOENIXLTD | B59: The Phoenix Mills Limited | C59: 0 | D59: 2025-10-16 | E59: 1694.9 | F59: 2025-10-16 | G59: 1694.9 | H59: 1 | I59: New | J59: -0.42 | K59: -0.84 | L59: 2.99 | M59: 11.79 | N59: 5.16 | O59: 1952.2 | P59: 15.18
A60: TATACONSUM | B60: TATA CONSUMER PRODUCTS LIMITED | C60: 1 | D60: 2025-10-16 | E60: 1149.3 | F60: 2025-10-16 | G60: 1149.3 | H60: 1 | I60: New | J60: 1.45 | K60: 0.52 | L60: 2.58 | M60: 3.49 | N60: -4.06 | O60: 960 | P60: -16.47
A61: BHARTIARTL | B61: Bharti Airtel Limited | C61: 0 | D61: 2025-10-17 | E61: 2012 | F61: 2025-10-17 | G61: 2012 | H61: 1 | I61: New | J61: 1.96 | K61: 3.38 | L61: 6.82 | M61: 0.52 | N61: -8.21 | O61: 1771.4 | P61: -11.96
A62: HINDUNILVR | B62: Hindustan Unilever Limited | C62: 0 | D62: 2025-10-17 | E62: 2603.7 | F62: 2025-10-17 | G62: 2603.7 | H62: 1 | I62: New | J62: -0.36 | K62: -3.53 | L62: -7.67 | M62: -9.61 | N62: -13.94 | O62: 1896 | P62: -27.18
A63: MANKIND | B63: Mankind Pharma Limited | C63: 1 | D63: 2025-10-17 | E63: 2476.6 | F63: 2025-10-17 | G63: 2476.6 | H63: 1 | I63: New | J63: -0.87 | K63: -2.42 | L63: -10.08 | M63: -9.38 | N63: -14.2 | O63: 2435.6 | P63: -1.66
A64: PIDILITIND | B64: Pidilite Industries Limited | C64: 1 | D64: 2025-10-17 | E64: 1542.7 | F64: 2025-10-17 | G64: 1542.7 | H64: 1 | I64: New | J64: -1.06 | K64: -2.48 | L64: -3.35 | M64: -3.07 | N64: -9.68 | O64: 1503 | P64: -2.57
A65: CIPLA | B65: Cipla Limited | C65: 1 | D65: 2025-10-20 | E65: 1639.1 | F65: 2025-10-20 | G65: 1639.1 | H65: 1 | I65: New | J65: 1.49 | K65: -4.33 | L65: -6.85 | M65: -14.74 | N65: -24.99 | O65: 1383.7 | P65: -15.58
A66: BIOCON | B66: Biocon Limited | C66: 1 | D66: 2025-10-29 | E66: 373.7 | F66: 2025-10-30 | G66: 376.6 | H66: 2 | I66: Active | J66: 0.78 | K66: 3.08 | L66: 6.94 | M66: -2.26 | N66: -2.92 | O66: 374.9 | P66: 0.32
A67: DLF | B67: DLF Limited | C67: 0 | D67: 2025-10-29 | E67: 778.7 | F67: 2025-10-29 | G67: 778.7 | H67: 1 | I67: New | J67: -0.28 | K67: -2.61 | L67: -6.84 | M67: -21.72 | N67: -24.5 | O67: 663.55 | P67: -14.79
A68: GAIL | B68: GAIL (India) Limited | C68: 0 | D68: 2025-10-29 | E68: 184.64 | F68: 2025-10-29 | G68: 184.64 | H68: 1 | I68: New | J68: -0.84 | K68: -3.07 | L68: -0.45 | M68: -13.36 | N68: -10.27 | O68: 172.45 | P68: -6.6
A69: GMRAIRPORT | B69: GMR AIRPORTS LIMITED | C69: 0 | D69: 2025-10-29 | E69: 92.97 | F69: 2025-10-30 | G69: 94.47 | H69: 2 | I69: Active | J69: 1.61 | K69: 1.59 | L69: 14.76 | M69: -0.35 | N69: 5.26 | O69: 94.75 | P69: 1.91
A70: IRCTC | B70: Indian Railway Catering And Tourism Corporation Limited | C70: 0 | D70: 2025-10-29 | E70: 730.65 | F70: 2025-10-29 | G70: 730.65 | H70: 1 | I70: New | J70: -0.34 | K70: -3.74 | L70: -5.86 | M70: -16.85 | N70: -25.57 | O70: 453.5 | P70: -37.93
... A106: ICICIPRULI | B106: ICICI Prudential Life Insurance Company Limited | C106: 0 | D106: 2025-11-12 | E106: 632.95 | F106: 2025-11-12 | G106: 632.95 | H106: 1 | I106: New | J106: -0.45 | K106: -3 | L106: 1.56 | M106: 2.43 | N106: -14.45 | O106: 458.7 | P106: -27.53
A107: LTIM | B107: N/A | C107: 1 | D107: 2025-11-12 | E107: 5893.5 | F107: 2025-11-12 | G107: 5893.5 | H107: 1 | I107: New | J107: -0.79 | K107: 1.33 | L107: 5.55 | M107: -4.53 | N107: INSUFFICIENT_FUTURE_DATA | O107: N/A | P107: N/A
A108: MOTHERSON | B108: Samvardhana Motherson International Limited | C108: 0 | D108: 2025-11-12 | E108: 105.92 | F108: 2025-11-12 | G108: 105.92 | H108: 1 | I108: New | J108: 3.03 | K108: 5.89 | L108: 9.78 | M108: 17.46 | N108: 17.31 | O108: 162.37 | P108: 53.29
A109: SRF | B109: SRF Limited | C109: 2 | D109: 2025-11-12 | E109: 2941.4 | F109: 2025-11-12 | G109: 2941.4 | H109: 1 | I109: New | J109: -1 | K109: -5.27 | L109: -0.33 | M109: 1.54 | N109: -7.49 | O109: 2491.5 | P109: -15.3
A110: SYNGENE | B110: Syngene International Limited | C110: 0 | D110: 2025-11-12 | E110: 663.85 | F110: 2025-11-12 | G110: 663.85 | H110: 1 | I110: New | J110: -0.26 | K110: -4.37 | L110: -5.2 | M110: -31.39 | N110: -27.88 | O110: 376 | P110: -43.36
A111: NMDC | B111: NMDC Limited | C111: 1 | D111: 2025-11-13 | E111: 77.39 | F111: 2025-11-13 | G111: 77.39 | H111: 1 | I111: New | J111: -1.09 | K111: -3.79 | L111: -2.69 | M111: 9.92 | N111: 17.73 | O111: 77.43 | P111: 0.05
A112: ASIANPAINT | B112: Asian Paints Limited | C112: 1 | D112: 2025-11-14 | E112: 2906.4 | F112: 2025-11-14 | G112: 2906.4 | H112: 1 | I112: New | J112: -0.64 | K112: -1.03 | L112: -4.87 | M112: -17.68 | N112: -9.78 | O112: 2420 | P112: -16.74
A113: AUROPHARMA | B113: Aurobindo Pharma Limited | C113: 0 | D113: 2025-11-14 | E113: 1222.5 | F113: 2025-11-14 | G113: 1222.5 | H113: 1 | I113: New | J113: 1.18 | K113: -1.36 | L113: -2.24 | M113: -6.21 | N113: 23.59 | O113: 1697.5 | P113: 38.85
A114: SIEMENS | B114: Siemens Limited | C114: 0 | D114: 2025-11-14 | E114: 3084.2 | F114: 2025-11-14 | G114: 3084.2 | H114: 1 | I114: New | J114: 4.81 | K114: 2.9 | L114: 1.96 | M114: 2.19 | N114: 19.77 | O114: 3785.5 | P114: 22.74
A115: POLICYBZR | B115: PB Fintech Limited | C115: 0 | D115: 2025-11-17 | E115: 1815.7 | F115: 2025-11-17 | G115: 1815.7 | H115: 1 | I115: New | J115: -0.85 | K115: -1.89 | L115: 6.1 | M115: -14.44 | N115: -7.02 | O115: 1151.3 | P115: -36.59
A116: CONCOR | B116: Container Corporation of India Limited | C116: 1 | D116: 2025-11-18 | E116: 522.6 | F116: 2025-11-18 | G116: 522.6 | H116: 1 | I116: New | J116: -0.97 | K116: -1.93 | L116: -4.4 | M116: -4.65 | N116: -3.95 | O116: 450 | P116: -13.89
A117: TECHM | B117: Tech Mahindra Limited | C117: 2 | D117: 2025-11-19 | E117: 1433.9 | F117: 2025-11-19 | G117: 1433.9 | H117: 1 | I117: New | J117: 1.54 | K117: 6.03 | L117: 10.15 | M117: 5.5 | N117: 2.32 | O117: 1542.2 | P117: 7.55
A118: AUBANK | B118: AU Small Finance Bank Limited | C118: 0 | D118: 2025-11-26 | E118: 953.75 | F118: 2025-11-26 | G118: 953.75 | H118: 1 | I118: New | J118: -0.69 | K118: -0.53 | L118: 2.13 | M118: 2.13 | N118: 6.09 | O118: 995.3 | P118: 4.36
A119: HDFCLIFE | B119: HDFC Life Insurance Company Limited | C119: 0 | D119: 2025-11-26 | E119: 787.55 | F119: 2025-11-26 | G119: 787.55 | H119: 1 | I119: New | J119: -1.24 | K119: -4.52 | L119: -4.09 | M119: -5.73 | N119: -21.42 | O119: 531.6 | P119: -32.5
... A125: CUMMINSIND | B125: Cummins India Limited | C125: 1 | D125: 2025-11-28 | E125: 4479.3 | F125: 2025-11-28 | G125: 4479.3 | H125: 1 | I125: New | J125: 1.45 | K125: -0.23 | L125: -1.72 | M125: 9.81 | N125: 31.29 | O125: 4855 | P125: 8.39
A126: NUVAMA | B126: Nuvama Wealth Management Limited | C126: 0 | D126: 2025-11-28 | E126: 7462.5 | F126: 2025-11-28 | G126: 7462.5 | H126: 1 | I126: New | J126: -0.13 | K126: -3.89 | L126: -80.42 | M126: -82.92 | N126: -79.17 | O126: 1640.6 | P126: -78.02 | Q126: Y
A127: JSWSTEEL | B127: JSW Steel Limited | C127: 2 | D127: 2025-12-01 | E127: 1168.4 | F127: 2025-12-01 | G127: 1168.4 | H127: 1 | I127: New | J127: -0.55 | K127: -4.22 | L127: -4.86 | M127: 9.6 | N127: 11.21 | O127: 1264.1 | P127: 8.19
A128: NMDC | B128: NMDC Limited | C128: 2 | D128: 2025-12-01 | E128: 75.39 | F128: 2025-12-01 | G128: 75.39 | H128: 1 | I128: New | J128: 0.93 | K128: -0.97 | L128: 10.64 | M128: 9.51 | N128: 22.52 | O128: 77.43 | P128: 2.71
A129: MOTHERSON | B129: Samvardhana Motherson International Limited | C129: 1 | D129: 2025-12-02 | E129: 119.26 | F129: 2025-12-02 | G129: 119.26 | H129: 1 | I129: New | J129: -2.26 | K129: -2.1 | L129: 0.57 | M129: 11.81 | N129: 21.49 | O129: 162.37 | P129: 36.15
A130: SHREECEM | B130: SHREE CEMENT LIMITED | C130: 0 | D130: 2025-12-02 | E130: 26545 | F130: 2025-12-02 | G130: 26545 | H130: 1 | I130: New | J130: -0.92 | K130: -1.68 | L130: 0.11 | M130: -1.77 | N130: -5.84 | O130: 22170 | P130: -16.48
A131: ADANIENT | B131: Adani Enterprises Limited | C131: 0 | D131: 2025-12-04 | E131: 2217.9 | F131: 2025-12-04 | G131: 2217.9 | H131: 1 | I131: New | J131: 2.14 | K131: 2.7 | L131: 2.79 | M131: -6.38 | N131: 34.04 | O131: 2831.1 | P131: 27.65
A132: PERSISTENT | B132: Persistent Systems Limited | C132: 1 | D132: 2025-12-04 | E132: 6452 | F132: 2025-12-04 | G132: 6452 | H132: 1 | I132: New | J132: 1.06 | K132: -3.84 | L132: -2.52 | M132: -27.01 | N132: -20.62 | O132: 5328.5 | P132: -17.41
A133: FEDERALBNK | B133: The Federal Bank Limited | C133: 1 | D133: 2025-12-09 | E133: 260.85 | F133: 2025-12-09 | G133: 260.85 | H133: 1 | I133: New | J133: -0.48 | K133: 0.52 | L133: -0.88 | M133: 4.77 | N133: 20.8 | O133: 325 | P133: 24.59
A134: AUBANK | B134: AU Small Finance Bank Limited | C134: 1 | D134: 2025-12-10 | E134: 993.7 | F134: 2025-12-10 | G134: 993.7 | H134: 1 | I134: New | J134: -2.08 | K134: -0.34 | L134: -0.16 | M134: -5.55 | N134: -3.47 | O134: 995.3 | P134: 0.16
A135: ICICIPRULI | B135: ICICI Prudential Life Insurance Company Limited | C135: 1 | D135: 2025-12-10 | E135: 642.85 | F135: 2025-12-10 | G135: 642.85 | H135: 1 | I135: New | J135: -1.09 | K135: -1.92 | L135: 5.99 | M135: -6.41 | N135: -27.54 | O135: 458.7 | P135: -28.65
A136: PFC | B136: Power Finance Corporation Limited | C136: 1 | D136: 2025-12-10 | E136: 343.85 | F136: 2025-12-10 | G136: 343.85 | H136: 1 | I136: New | J136: -0.38 | K136: -2.38 | L136: 6.28 | M136: 19.86 | N136: 25.43 | O136: 330 | P136: -4.03
A137: AMBUJACEM | B137: Ambuja Cements Limited | C137: 0 | D137: 2025-12-11 | E137: 536.1 | F137: 2025-12-11 | G137: 536.1 | H137: 1 | I137: New | J137: 2.25 | K137: -0.06 | L137: 0.16 | M137: -14.61 | N137: -24.26 | O137: 374.35 | P137: -30.17
A138: MOTHERSON | B138: Samvardhana Motherson International Limited | C138: 2 | D138: 2025-12-11 | E138: 119.8 | F138: 2025-12-11 | G138: 119.8 | H138: 1 | I138: New | J138: 1.25 | K138: -2.21 | L138: -3.47 | M138: 1.33 | N138: 17.48 | O138: 162.37 | P138: 35.53
... A150: TATAPOWER | B150: Tata Power Company Limited | C150: 1 | D150: 2025-12-12 | E150: 381.95 | F150: 2025-12-12 | G150: 381.95 | H150: 1 | I150: New | J150: -0.08 | K150: -0.37 | L150: -2.97 | M150: 5.29 | N150: 3.04 | O150: 361.9 | P150: -5.25
A151: VEDL | B151: Vedanta Limited | C151: 1 | D151: 2025-12-12 | E151: 543.6 | F151: 2025-12-12 | G151: 543.6 | H151: 1 | I151: New | J151: 1.07 | K151: 6.99 | L151: 15.41 | M151: 32.38 | N151: -43.04 | O151: 259 | P151: -52.35 | Q151: Y
A152: PHOENIXLTD | B152: The Phoenix Mills Limited | C152: 1 | D152: 2025-12-15 | E152: 1789.4 | F152: 2025-12-15 | G152: 1789.4 | H152: 1 | I152: New | J152: -0.47 | K152: 3.22 | L152: 5.88 | M152: -12.51 | N152: 3.21 | O152: 1952.2 | P152: 9.1
A153: APLAPOLLO | B153: APL Apollo Tubes Limited | C153: 1 | D153: 2025-12-17 | E153: 1764.5 | F153: 2025-12-17 | G153: 1764.5 | H153: 1 | I153: New | J153: 1.77 | K153: 5.33 | L153: 9.99 | M153: 11.4 | N153: 5.11 | O153: 2197 | P153: 24.51
A154: AUBANK | B154: AU Small Finance Bank Limited | C154: 2 | D154: 2025-12-17 | E154: 990.3 | F154: 2025-12-17 | G154: 990.3 | H154: 1 | I154: New | J154: -0.27 | K154: -1.64 | L154: 3.54 | M154: -8.91 | N154: 3.08 | O154: 995.3 | P154: 0.5
A155: IOC | B155: Indian Oil Corporation Limited | C155: 5 | D155: 2025-12-17 | E155: 168.16 | F155: 2025-12-17 | G155: 168.16 | H155: 1 | I155: New | J155: -3.81 | K155: -4.16 | L155: -4.07 | M155: -12.77 | N155: -13.52 | O155: 133.32 | P155: -20.72
A156: LTIM | B156: N/A | C156: 2 | D156: 2025-12-17 | E156: 6252.5 | F156: 2025-12-17 | G156: 6252.5 | H156: 1 | I156: New | J156: -0.12 | K156: -1.43 | L156: 0.89 | M156: INSUFFICIENT_FUTURE_DATA | N156: INSUFFICIENT_FUTURE_DATA | O156: N/A | P156: N/A
A157: PATANJALI | B157: Patanjali Foods Limited | C157: 1 | D157: 2025-12-17 | E157: 543.9 | F157: 2025-12-17 | G157: 543.9 | H157: 1 | I157: New | J157: 1.18 | K157: 0.61 | L157: -4.1 | M157: -10.56 | N157: -22.96 | O157: 390.8 | P157: -28.15
...

Sheet Missing_History
A1: Date | B1: Reason V15 result cannot be established (MISSING ≠ ZERO)
A2: 2025-09-02 | B2: warm-up: engine needs 20 prior sessions, no verdict possible
A3: 2025-09-03 | B3: warm-up: engine needs 20 prior sessions, no verdict possible
A4: 2025-09-04 | B4: warm-up: engine needs 20 prior sessions, no verdict possible
A5: 2025-09-05 | B5: warm-up: engine needs 20 prior sessions, no verdict possible
A6: 2025-09-08 | B6: warm-up: engine needs 20 prior sessions, no verdict possible
A7: 2025-09-09 | B7: warm-up: engine needs 20 prior sessions, no verdict possible
A8: 2025-09-10 | B8: warm-up: engine needs 20 prior sessions, no verdict possible
A9: 2025-09-11 | B9: warm-up: engine needs 20 prior sessions, no verdict possible
A10: 2025-09-12 | B10: warm-up: engine needs 20 prior sessions, no verdict possible
A11: 2025-09-15 | B11: warm-up: engine needs 20 prior sessions, no verdict possible
A12: 2025-09-16 | B12: warm-up: engine needs 20 prior sessions, no verdict possible
... A35: 2026-09-24 | B35: no recorded V15 run covers this date (raw files exist, no verdicts stored)
